{
  "summary": {
    "official_id": "ron-garretson",
    "name": "Ron Garretson",
    "slug": "ron-garretson",
    "raw_ids": [
      "1164",
      "espn:ron-garretson"
    ],
    "eras": [
      "espn",
      "nba"
    ],
    "first_season": "2000-01",
    "last_season": "2018-19",
    "games_total": 1254,
    "games_rs": 1124,
    "games_po": 130,
    "games_pi": 0,
    "finals_games": 3,
    "game7s": 3,
    "active": false,
    "per_season": {
      "2000-01": {
        "rs": 68,
        "po": 8,
        "pi": 0,
        "total": 76
      },
      "2001-02": {
        "rs": 68,
        "po": 9,
        "pi": 0,
        "total": 77
      },
      "2002-03": {
        "rs": 68,
        "po": 12,
        "pi": 0,
        "total": 80
      },
      "2003-04": {
        "rs": 55,
        "po": 10,
        "pi": 0,
        "total": 65
      },
      "2004-05": {
        "rs": 60,
        "po": 12,
        "pi": 0,
        "total": 72
      },
      "2005-06": {
        "rs": 60,
        "po": 0,
        "pi": 0,
        "total": 60
      },
      "2006-07": {
        "rs": 56,
        "po": 8,
        "pi": 0,
        "total": 64
      },
      "2007-08": {
        "rs": 61,
        "po": 6,
        "pi": 0,
        "total": 67
      },
      "2008-09": {
        "rs": 59,
        "po": 10,
        "pi": 0,
        "total": 69
      },
      "2009-10": {
        "rs": 61,
        "po": 4,
        "pi": 0,
        "total": 65
      },
      "2010-11": {
        "rs": 66,
        "po": 10,
        "pi": 0,
        "total": 76
      },
      "2011-12": {
        "rs": 49,
        "po": 9,
        "pi": 0,
        "total": 58
      },
      "2012-13": {
        "rs": 64,
        "po": 9,
        "pi": 0,
        "total": 73
      },
      "2013-14": {
        "rs": 52,
        "po": 8,
        "pi": 0,
        "total": 60
      },
      "2014-15": {
        "rs": 57,
        "po": 4,
        "pi": 0,
        "total": 61
      },
      "2015-16": {
        "rs": 61,
        "po": 3,
        "pi": 0,
        "total": 64
      },
      "2016-17": {
        "rs": 53,
        "po": 5,
        "pi": 0,
        "total": 58
      },
      "2017-18": {
        "rs": 53,
        "po": 3,
        "pi": 0,
        "total": 56
      },
      "2018-19": {
        "rs": 53,
        "po": 0,
        "pi": 0,
        "total": 53
      }
    }
  },
  "team_records": [
    {
      "team_abbr": "LAL",
      "games": 113,
      "wins": 58,
      "losses": 55,
      "win_pct": 0.51,
      "home_games": 66,
      "home_wins": 42,
      "avg_margin_for_team": 0.88
    },
    {
      "team_abbr": "PHX",
      "games": 106,
      "wins": 58,
      "losses": 48,
      "win_pct": 0.55,
      "home_games": 61,
      "home_wins": 45,
      "avg_margin_for_team": 0.73
    },
    {
      "team_abbr": "DEN",
      "games": 106,
      "wins": 59,
      "losses": 47,
      "win_pct": 0.56,
      "home_games": 60,
      "home_wins": 40,
      "avg_margin_for_team": -0.33
    },
    {
      "team_abbr": "SAS",
      "games": 104,
      "wins": 73,
      "losses": 31,
      "win_pct": 0.7,
      "home_games": 48,
      "home_wins": 39,
      "avg_margin_for_team": 6.39
    },
    {
      "team_abbr": "POR",
      "games": 98,
      "wins": 59,
      "losses": 39,
      "win_pct": 0.6,
      "home_games": 58,
      "home_wins": 44,
      "avg_margin_for_team": 4.08
    },
    {
      "team_abbr": "GSW",
      "games": 94,
      "wins": 46,
      "losses": 48,
      "win_pct": 0.49,
      "home_games": 46,
      "home_wins": 27,
      "avg_margin_for_team": -0.33
    },
    {
      "team_abbr": "UTA",
      "games": 93,
      "wins": 51,
      "losses": 42,
      "win_pct": 0.55,
      "home_games": 37,
      "home_wins": 25,
      "avg_margin_for_team": 1.83
    },
    {
      "team_abbr": "LAC",
      "games": 92,
      "wins": 45,
      "losses": 47,
      "win_pct": 0.49,
      "home_games": 65,
      "home_wins": 34,
      "avg_margin_for_team": 0.89
    },
    {
      "team_abbr": "BOS",
      "games": 88,
      "wins": 35,
      "losses": 53,
      "win_pct": 0.4,
      "home_games": 42,
      "home_wins": 21,
      "avg_margin_for_team": -2.1
    },
    {
      "team_abbr": "SAC",
      "games": 85,
      "wins": 36,
      "losses": 49,
      "win_pct": 0.42,
      "home_games": 48,
      "home_wins": 28,
      "avg_margin_for_team": -1.48
    },
    {
      "team_abbr": "CHI",
      "games": 84,
      "wins": 39,
      "losses": 45,
      "win_pct": 0.46,
      "home_games": 37,
      "home_wins": 26,
      "avg_margin_for_team": -0.94
    },
    {
      "team_abbr": "IND",
      "games": 84,
      "wins": 52,
      "losses": 32,
      "win_pct": 0.62,
      "home_games": 41,
      "home_wins": 29,
      "avg_margin_for_team": 3.4
    },
    {
      "team_abbr": "CLE",
      "games": 83,
      "wins": 43,
      "losses": 40,
      "win_pct": 0.52,
      "home_games": 42,
      "home_wins": 26,
      "avg_margin_for_team": 0.1
    },
    {
      "team_abbr": "DET",
      "games": 83,
      "wins": 39,
      "losses": 44,
      "win_pct": 0.47,
      "home_games": 40,
      "home_wins": 25,
      "avg_margin_for_team": -1.28
    },
    {
      "team_abbr": "PHI",
      "games": 83,
      "wins": 36,
      "losses": 47,
      "win_pct": 0.43,
      "home_games": 39,
      "home_wins": 19,
      "avg_margin_for_team": -2.8
    },
    {
      "team_abbr": "DAL",
      "games": 83,
      "wins": 36,
      "losses": 47,
      "win_pct": 0.43,
      "home_games": 30,
      "home_wins": 15,
      "avg_margin_for_team": -0.65
    },
    {
      "team_abbr": "MEM",
      "games": 83,
      "wins": 43,
      "losses": 40,
      "win_pct": 0.52,
      "home_games": 40,
      "home_wins": 27,
      "avg_margin_for_team": 0.37
    },
    {
      "team_abbr": "HOU",
      "games": 77,
      "wins": 46,
      "losses": 31,
      "win_pct": 0.6,
      "home_games": 38,
      "home_wins": 29,
      "avg_margin_for_team": 2.47
    },
    {
      "team_abbr": "WAS",
      "games": 74,
      "wins": 32,
      "losses": 42,
      "win_pct": 0.43,
      "home_games": 32,
      "home_wins": 20,
      "avg_margin_for_team": -3.23
    },
    {
      "team_abbr": "NYK",
      "games": 72,
      "wins": 23,
      "losses": 49,
      "win_pct": 0.32,
      "home_games": 35,
      "home_wins": 16,
      "avg_margin_for_team": -4.43
    },
    {
      "team_abbr": "MIL",
      "games": 71,
      "wins": 34,
      "losses": 37,
      "win_pct": 0.48,
      "home_games": 37,
      "home_wins": 23,
      "avg_margin_for_team": 0.37
    },
    {
      "team_abbr": "ORL",
      "games": 71,
      "wins": 29,
      "losses": 42,
      "win_pct": 0.41,
      "home_games": 26,
      "home_wins": 16,
      "avg_margin_for_team": -2.34
    },
    {
      "team_abbr": "ATL",
      "games": 71,
      "wins": 32,
      "losses": 39,
      "win_pct": 0.45,
      "home_games": 36,
      "home_wins": 20,
      "avg_margin_for_team": -1.45
    },
    {
      "team_abbr": "TOR",
      "games": 68,
      "wins": 36,
      "losses": 32,
      "win_pct": 0.53,
      "home_games": 38,
      "home_wins": 24,
      "avg_margin_for_team": 1.0
    },
    {
      "team_abbr": "MIN",
      "games": 68,
      "wins": 35,
      "losses": 33,
      "win_pct": 0.51,
      "home_games": 31,
      "home_wins": 18,
      "avg_margin_for_team": -0.74
    },
    {
      "team_abbr": "MIA",
      "games": 68,
      "wins": 43,
      "losses": 25,
      "win_pct": 0.63,
      "home_games": 36,
      "home_wins": 28,
      "avg_margin_for_team": 3.9
    },
    {
      "team_abbr": "CHA",
      "games": 67,
      "wins": 30,
      "losses": 37,
      "win_pct": 0.45,
      "home_games": 27,
      "home_wins": 19,
      "avg_margin_for_team": -2.3
    },
    {
      "team_abbr": "OKC",
      "games": 52,
      "wins": 29,
      "losses": 23,
      "win_pct": 0.56,
      "home_games": 25,
      "home_wins": 16,
      "avg_margin_for_team": 2.02
    },
    {
      "team_abbr": "NJN",
      "games": 50,
      "wins": 22,
      "losses": 28,
      "win_pct": 0.44,
      "home_games": 27,
      "home_wins": 15,
      "avg_margin_for_team": -2.14
    },
    {
      "team_abbr": "NOH",
      "games": 33,
      "wins": 14,
      "losses": 19,
      "win_pct": 0.42,
      "home_games": 17,
      "home_wins": 7,
      "avg_margin_for_team": -2.94
    },
    {
      "team_abbr": "SEA",
      "games": 32,
      "wins": 14,
      "losses": 18,
      "win_pct": 0.44,
      "home_games": 21,
      "home_wins": 10,
      "avg_margin_for_team": -3.41
    },
    {
      "team_abbr": "NOP",
      "games": 31,
      "wins": 15,
      "losses": 16,
      "win_pct": 0.48,
      "home_games": 12,
      "home_wins": 8,
      "avg_margin_for_team": -1.74
    },
    {
      "team_abbr": "BKN",
      "games": 26,
      "wins": 8,
      "losses": 18,
      "win_pct": 0.31,
      "home_games": 11,
      "home_wins": 5,
      "avg_margin_for_team": -5.46
    },
    {
      "team_abbr": "NOK",
      "games": 8,
      "wins": 2,
      "losses": 6,
      "win_pct": 0.25,
      "home_games": 2,
      "home_wins": 0,
      "avg_margin_for_team": -5.75
    },
    {
      "team_abbr": "VAN",
      "games": 7,
      "wins": 2,
      "losses": 5,
      "win_pct": 0.29,
      "home_games": 3,
      "home_wins": 2,
      "avg_margin_for_team": -5.43
    }
  ],
  "whistle_profile": {
    "rs": {
      "n": 1124,
      "n_boxscore": 1124,
      "avg_total_points": 197.11,
      "avg_total_fta": 45.35,
      "avg_total_pf": 40.17,
      "home_win_pct": 0.63,
      "avg_abs_margin": 11.72,
      "ot_games": 54,
      "ot_rate": 0.05
    },
    "po": {
      "n": 130,
      "n_boxscore": 130,
      "avg_total_points": 189.36,
      "avg_total_fta": 49.31,
      "avg_total_pf": 43.62,
      "home_win_pct": 0.61,
      "avg_abs_margin": 11.19,
      "ot_games": 7,
      "ot_rate": 0.05
    }
  },
  "top_performances": [
    {
      "player_name": "Damian Lillard",
      "pts": 59,
      "team_abbr": "POR",
      "opp_abbr": "UTA",
      "game_date": "2017-04-08",
      "game_id": "0021601194"
    },
    {
      "player_name": "Jermaine O'Neal",
      "pts": 55,
      "team_abbr": "IND",
      "opp_abbr": "MIL",
      "game_date": "2005-01-04",
      "game_id": "0020400449"
    },
    {
      "player_name": "Jimmy Butler",
      "pts": 52,
      "team_abbr": "CHI",
      "opp_abbr": "CHA",
      "game_date": "2017-01-02",
      "game_id": "0021600517"
    },
    {
      "player_name": "CJ McCollum",
      "pts": 50,
      "team_abbr": "POR",
      "opp_abbr": "CHI",
      "game_date": "2018-01-31",
      "game_id": "0021700759"
    },
    {
      "player_name": "LeBron James",
      "pts": 49,
      "team_abbr": "CLE",
      "opp_abbr": "ORL",
      "game_date": "2009-05-20",
      "game_id": "0040800301"
    },
    {
      "player_name": "Kevin Martin",
      "pts": 48,
      "team_abbr": "SAC",
      "opp_abbr": "MIN",
      "game_date": "2008-03-07",
      "game_id": "0020700921"
    },
    {
      "player_name": "Anthony Davis",
      "pts": 48,
      "team_abbr": "NOP",
      "opp_abbr": "NYK",
      "game_date": "2018-01-14",
      "game_id": "0021700635"
    },
    {
      "player_name": "Stephen Curry",
      "pts": 48,
      "team_abbr": "GSW",
      "opp_abbr": "DAL",
      "game_date": "2019-01-13",
      "game_id": "0021800642"
    },
    {
      "player_name": "Anthony Davis",
      "pts": 47,
      "team_abbr": "NOP",
      "opp_abbr": "POR",
      "game_date": "2018-04-21",
      "game_id": "0041700164"
    },
    {
      "player_name": "Antoine Walker",
      "pts": 47,
      "team_abbr": "BOS",
      "opp_abbr": "SAC",
      "game_date": "2001-01-18",
      "game_id": "210117023"
    },
    {
      "player_name": "LeBron James",
      "pts": 46,
      "team_abbr": "CLE",
      "opp_abbr": "DAL",
      "game_date": "2006-03-29",
      "game_id": "0020501057"
    },
    {
      "player_name": "Kyrie Irving",
      "pts": 46,
      "team_abbr": "CLE",
      "opp_abbr": "LAL",
      "game_date": "2017-03-19",
      "game_id": "0021601043"
    },
    {
      "player_name": "Russell Westbrook",
      "pts": 46,
      "team_abbr": "OKC",
      "opp_abbr": "WAS",
      "game_date": "2018-01-25",
      "game_id": "0021700711"
    },
    {
      "player_name": "Dwight Howard",
      "pts": 46,
      "team_abbr": "ORL",
      "opp_abbr": "ATL",
      "game_date": "2011-04-16",
      "game_id": "0041000131"
    },
    {
      "player_name": "Russell Westbrook",
      "pts": 46,
      "team_abbr": "OKC",
      "opp_abbr": "UTA",
      "game_date": "2018-04-27",
      "game_id": "0041700176"
    },
    {
      "player_name": "LaMarcus Aldridge",
      "pts": 45,
      "team_abbr": "SAS",
      "opp_abbr": "UTA",
      "game_date": "2018-03-23",
      "game_id": "0021701085"
    },
    {
      "player_name": "Allen Iverson",
      "pts": 45,
      "team_abbr": "PHI",
      "opp_abbr": "UTA",
      "game_date": "2000-12-21",
      "game_id": "201220020"
    },
    {
      "player_name": "Kobe Bryant",
      "pts": 45,
      "team_abbr": "LAL",
      "opp_abbr": "SAS",
      "game_date": "2001-05-19",
      "game_id": "210519024"
    },
    {
      "player_name": "Gilbert Arenas",
      "pts": 44,
      "team_abbr": "WAS",
      "opp_abbr": "BOS",
      "game_date": "2006-11-04",
      "game_id": "0020600031"
    },
    {
      "player_name": "Ray Allen",
      "pts": 44,
      "team_abbr": "SEA",
      "opp_abbr": "DEN",
      "game_date": "2007-01-23",
      "game_id": "0020600619"
    },
    {
      "player_name": "Allen Iverson",
      "pts": 44,
      "team_abbr": "DEN",
      "opp_abbr": "PHX",
      "game_date": "2007-03-17",
      "game_id": "0020600986"
    },
    {
      "player_name": "Carmelo Anthony",
      "pts": 44,
      "team_abbr": "NYK",
      "opp_abbr": "ORL",
      "game_date": "2014-02-21",
      "game_id": "0021300816"
    },
    {
      "player_name": "Derrick Rose",
      "pts": 44,
      "team_abbr": "CHI",
      "opp_abbr": "ATL",
      "game_date": "2011-05-06",
      "game_id": "0041000203"
    },
    {
      "player_name": "Allen Iverson",
      "pts": 44,
      "team_abbr": "PHI",
      "opp_abbr": "DET",
      "game_date": "2001-01-27",
      "game_id": "210126020"
    },
    {
      "player_name": "Shaquille O'Neal",
      "pts": 44,
      "team_abbr": "LAL",
      "opp_abbr": "SAC",
      "game_date": "2001-05-06",
      "game_id": "210506013"
    }
  ],
  "player_swings": [
    {
      "player_id": "63",
      "name": "Chauncey Billups",
      "n_games": 15,
      "pts_with_ref": 18.47,
      "pts_baseline": 12.75,
      "pts_swing": 5.71,
      "fta_swing": 2.1,
      "pf_swing": 0.09
    },
    {
      "player_id": "201156",
      "name": "Nick Young",
      "n_games": 32,
      "pts_with_ref": 15.28,
      "pts_baseline": 10.92,
      "pts_swing": 4.36,
      "fta_swing": 0.31,
      "pf_swing": 0.2
    },
    {
      "player_id": "556",
      "name": "Brad Miller",
      "n_games": 16,
      "pts_with_ref": 16.69,
      "pts_baseline": 12.5,
      "pts_swing": 4.19,
      "fta_swing": 0.74,
      "pf_swing": 0.3
    },
    {
      "player_id": "202710",
      "name": "Jimmy Butler",
      "n_games": 16,
      "pts_with_ref": 22.38,
      "pts_baseline": 18.22,
      "pts_swing": 4.16,
      "fta_swing": 0.26,
      "pf_swing": 0.17
    },
    {
      "player_id": "1626144",
      "name": "Emmanuel Mudiay",
      "n_games": 16,
      "pts_with_ref": 7.56,
      "pts_baseline": 11.6,
      "pts_swing": -4.03,
      "fta_swing": -0.5,
      "pf_swing": -0.14
    },
    {
      "player_id": "294",
      "name": "Richard Hamilton",
      "n_games": 18,
      "pts_with_ref": 14.78,
      "pts_baseline": 18.56,
      "pts_swing": -3.79,
      "fta_swing": -1.95,
      "pf_swing": -0.01
    },
    {
      "player_id": "509",
      "name": "Stephon Marbury",
      "n_games": 15,
      "pts_with_ref": 18.2,
      "pts_baseline": 21.83,
      "pts_swing": -3.63,
      "fta_swing": -1.73,
      "pf_swing": -0.85
    },
    {
      "player_id": "203076",
      "name": "Anthony Davis",
      "n_games": 21,
      "pts_with_ref": 22.24,
      "pts_baseline": 25.75,
      "pts_swing": -3.51,
      "fta_swing": -1.47,
      "pf_swing": 0.08
    },
    {
      "player_id": "1024",
      "name": "Jamaal Tinsley",
      "n_games": 15,
      "pts_with_ref": 10.33,
      "pts_baseline": 7.17,
      "pts_swing": 3.17,
      "fta_swing": -0.18,
      "pf_swing": -0.22
    },
    {
      "player_id": "201935",
      "name": "James Harden",
      "n_games": 37,
      "pts_with_ref": 18.49,
      "pts_baseline": 21.64,
      "pts_swing": -3.16,
      "fta_swing": -0.6,
      "pf_swing": 0.1
    },
    {
      "player_id": "862",
      "name": "Hedo Turkoglu",
      "n_games": 18,
      "pts_with_ref": 10.56,
      "pts_baseline": 7.49,
      "pts_swing": 3.07,
      "fta_swing": 0.44,
      "pf_swing": -0.15
    },
    {
      "player_id": "376",
      "name": "Bobby Jackson",
      "n_games": 17,
      "pts_with_ref": 7.65,
      "pts_baseline": 10.67,
      "pts_swing": -3.03,
      "fta_swing": -0.51,
      "pf_swing": -0.82
    },
    {
      "player_id": "201563",
      "name": "Michael Beasley",
      "n_games": 23,
      "pts_with_ref": 9.83,
      "pts_baseline": 12.76,
      "pts_swing": -2.93,
      "fta_swing": -0.4,
      "pf_swing": 0.16
    },
    {
      "player_id": "202718",
      "name": "Chandler Parsons",
      "n_games": 16,
      "pts_with_ref": 8.94,
      "pts_baseline": 11.85,
      "pts_swing": -2.91,
      "fta_swing": 0.38,
      "pf_swing": -0.6
    },
    {
      "player_id": "2072",
      "name": "Michael Redd",
      "n_games": 29,
      "pts_with_ref": 22.17,
      "pts_baseline": 19.31,
      "pts_swing": 2.86,
      "fta_swing": 0.41,
      "pf_swing": -0.07
    },
    {
      "player_id": "638",
      "name": "Ruben Patterson",
      "n_games": 19,
      "pts_with_ref": 7.68,
      "pts_baseline": 10.46,
      "pts_swing": -2.77,
      "fta_swing": 0.04,
      "pf_swing": -0.28
    },
    {
      "player_id": "2035",
      "name": "DerMarr Johnson",
      "n_games": 16,
      "pts_with_ref": 2.88,
      "pts_baseline": 5.61,
      "pts_swing": -2.74,
      "fta_swing": -0.4,
      "pf_swing": -0.51
    },
    {
      "player_id": "615",
      "name": "Jermaine O'Neal",
      "n_games": 22,
      "pts_with_ref": 18.23,
      "pts_baseline": 15.5,
      "pts_swing": 2.73,
      "fta_swing": -0.24,
      "pf_swing": -0.23
    },
    {
      "player_id": "56",
      "name": "Gary Payton",
      "n_games": 17,
      "pts_with_ref": 7.76,
      "pts_baseline": 10.43,
      "pts_swing": -2.66,
      "fta_swing": -0.68,
      "pf_swing": 0.25
    },
    {
      "player_id": "1626156",
      "name": "D'Angelo Russell",
      "n_games": 15,
      "pts_with_ref": 13.47,
      "pts_baseline": 16.09,
      "pts_swing": -2.63,
      "fta_swing": 0.48,
      "pf_swing": 0.02
    },
    {
      "player_id": "201163",
      "name": "Wilson Chandler",
      "n_games": 37,
      "pts_with_ref": 10.05,
      "pts_baseline": 12.67,
      "pts_swing": -2.62,
      "fta_swing": -0.97,
      "pf_swing": -0.15
    },
    {
      "player_id": "203999",
      "name": "Nikola Jokic",
      "n_games": 19,
      "pts_with_ref": 14.16,
      "pts_baseline": 16.73,
      "pts_swing": -2.57,
      "fta_swing": -1.59,
      "pf_swing": -0.31
    },
    {
      "player_id": "1627750",
      "name": "Jamal Murray",
      "n_games": 16,
      "pts_with_ref": 16.56,
      "pts_baseline": 14.0,
      "pts_swing": 2.56,
      "fta_swing": 1.19,
      "pf_swing": 0.34
    },
    {
      "player_id": "1891",
      "name": "Jason Terry",
      "n_games": 55,
      "pts_with_ref": 15.58,
      "pts_baseline": 13.07,
      "pts_swing": 2.51,
      "fta_swing": 0.15,
      "pf_swing": 0.24
    },
    {
      "player_id": "366",
      "name": "Allen Iverson",
      "n_games": 19,
      "pts_with_ref": 32.58,
      "pts_baseline": 30.11,
      "pts_swing": 2.47,
      "fta_swing": 0.86,
      "pf_swing": -0.07
    },
    {
      "player_id": "947",
      "name": "Allen Iverson",
      "n_games": 20,
      "pts_with_ref": 28.35,
      "pts_baseline": 25.89,
      "pts_swing": 2.46,
      "fta_swing": 0.11,
      "pf_swing": -0.25
    },
    {
      "player_id": "200769",
      "name": "Shannon Brown",
      "n_games": 26,
      "pts_with_ref": 10.62,
      "pts_baseline": 8.2,
      "pts_swing": 2.42,
      "fta_swing": 0.43,
      "pf_swing": 0.17
    },
    {
      "player_id": "2406",
      "name": "Caron Butler",
      "n_games": 38,
      "pts_with_ref": 11.39,
      "pts_baseline": 13.74,
      "pts_swing": -2.35,
      "fta_swing": 0.01,
      "pf_swing": -0.45
    },
    {
      "player_id": "429",
      "name": "Jason Kidd",
      "n_games": 24,
      "pts_with_ref": 13.67,
      "pts_baseline": 16.0,
      "pts_swing": -2.34,
      "fta_swing": -1.0,
      "pf_swing": -0.52
    },
    {
      "player_id": "682",
      "name": "Joel Przybilla",
      "n_games": 21,
      "pts_with_ref": 3.19,
      "pts_baseline": 5.51,
      "pts_swing": -2.32,
      "fta_swing": -0.22,
      "pf_swing": -0.34
    },
    {
      "player_id": "2229",
      "name": "Mike James",
      "n_games": 28,
      "pts_with_ref": 7.21,
      "pts_baseline": 9.49,
      "pts_swing": -2.27,
      "fta_swing": -1.09,
      "pf_swing": -0.52
    },
    {
      "player_id": "201971",
      "name": "DeJuan Blair",
      "n_games": 19,
      "pts_with_ref": 9.53,
      "pts_baseline": 7.27,
      "pts_swing": 2.26,
      "fta_swing": 0.45,
      "pf_swing": 0.21
    },
    {
      "player_id": "202702",
      "name": "Kenneth Faried",
      "n_games": 28,
      "pts_with_ref": 8.82,
      "pts_baseline": 11.07,
      "pts_swing": -2.25,
      "fta_swing": -0.16,
      "pf_swing": -0.25
    },
    {
      "player_id": "203482",
      "name": "Kelly Olynyk",
      "n_games": 17,
      "pts_with_ref": 7.47,
      "pts_baseline": 9.71,
      "pts_swing": -2.24,
      "fta_swing": -0.55,
      "pf_swing": -0.57
    },
    {
      "player_id": "203924",
      "name": "Jerami Grant",
      "n_games": 15,
      "pts_with_ref": 11.6,
      "pts_baseline": 9.37,
      "pts_swing": 2.23,
      "fta_swing": 0.11,
      "pf_swing": -0.69
    },
    {
      "player_id": "1863",
      "name": "Earl Boykins",
      "n_games": 23,
      "pts_with_ref": 8.43,
      "pts_baseline": 10.65,
      "pts_swing": -2.22,
      "fta_swing": -0.99,
      "pf_swing": 0.19
    },
    {
      "player_id": "2048",
      "name": "Jamaal Magloire",
      "n_games": 24,
      "pts_with_ref": 10.21,
      "pts_baseline": 8.0,
      "pts_swing": 2.21,
      "fta_swing": 0.97,
      "pf_swing": 0.23
    },
    {
      "player_id": "9",
      "name": "Ray Allen",
      "n_games": 17,
      "pts_with_ref": 18.0,
      "pts_baseline": 20.21,
      "pts_swing": -2.21,
      "fta_swing": -1.23,
      "pf_swing": -0.03
    },
    {
      "player_id": "183",
      "name": "Antonio Daniels",
      "n_games": 17,
      "pts_with_ref": 5.65,
      "pts_baseline": 7.84,
      "pts_swing": -2.2,
      "fta_swing": -0.25,
      "pf_swing": -0.08
    },
    {
      "player_id": "203501",
      "name": "Tim Hardaway Jr.",
      "n_games": 16,
      "pts_with_ref": 9.12,
      "pts_baseline": 11.31,
      "pts_swing": -2.19,
      "fta_swing": -0.42,
      "pf_swing": -0.02
    },
    {
      "player_id": "201571",
      "name": "D.J. Augustin",
      "n_games": 33,
      "pts_with_ref": 8.48,
      "pts_baseline": 10.66,
      "pts_swing": -2.18,
      "fta_swing": -0.62,
      "pf_swing": -0.37
    },
    {
      "player_id": "883",
      "name": "Rasheed Wallace",
      "n_games": 19,
      "pts_with_ref": 16.58,
      "pts_baseline": 18.76,
      "pts_swing": -2.18,
      "fta_swing": -1.72,
      "pf_swing": -0.24
    },
    {
      "player_id": "2045",
      "name": "Hedo Turkoglu",
      "n_games": 38,
      "pts_with_ref": 8.92,
      "pts_baseline": 11.1,
      "pts_swing": -2.17,
      "fta_swing": -0.73,
      "pf_swing": -0.43
    },
    {
      "player_id": "101145",
      "name": "Monta Ellis",
      "n_games": 37,
      "pts_with_ref": 16.08,
      "pts_baseline": 18.24,
      "pts_swing": -2.16,
      "fta_swing": -1.44,
      "pf_swing": -0.2
    },
    {
      "player_id": "202738",
      "name": "Isaiah Thomas",
      "n_games": 16,
      "pts_with_ref": 17.56,
      "pts_baseline": 19.72,
      "pts_swing": -2.16,
      "fta_swing": -1.33,
      "pf_swing": -0.62
    },
    {
      "player_id": "203118",
      "name": "Mike Scott",
      "n_games": 19,
      "pts_with_ref": 5.11,
      "pts_baseline": 7.27,
      "pts_swing": -2.16,
      "fta_swing": -0.61,
      "pf_swing": -0.09
    },
    {
      "player_id": "2036",
      "name": "Chris Mihm",
      "n_games": 16,
      "pts_with_ref": 6.44,
      "pts_baseline": 8.58,
      "pts_swing": -2.15,
      "fta_swing": -0.92,
      "pf_swing": -1.02
    },
    {
      "player_id": "202693",
      "name": "Markieff Morris",
      "n_games": 27,
      "pts_with_ref": 13.63,
      "pts_baseline": 11.49,
      "pts_swing": 2.14,
      "fta_swing": 0.78,
      "pf_swing": -0.27
    },
    {
      "player_id": "202338",
      "name": "Kevin Seraphin",
      "n_games": 15,
      "pts_with_ref": 3.33,
      "pts_baseline": 5.47,
      "pts_swing": -2.13,
      "fta_swing": 0.02,
      "pf_swing": -0.35
    },
    {
      "player_id": "110",
      "name": "Kobe Bryant",
      "n_games": 26,
      "pts_with_ref": 25.88,
      "pts_baseline": 28.01,
      "pts_swing": -2.13,
      "fta_swing": -0.85,
      "pf_swing": 0.07
    }
  ],
  "notable_games": [
    {
      "game_id": "0040800137",
      "date": "2009-05-03",
      "matchup": "MIA@ATL",
      "result": "ATL 91, MIA 78",
      "round": "Round 1",
      "game_num": 7
    },
    {
      "game_id": "0040400405",
      "date": "2005-06-19",
      "matchup": "SAS@DET",
      "result": "DET 95, SAS 96",
      "round": "Finals",
      "game_num": 5
    },
    {
      "game_id": "0040400401",
      "date": "2005-06-09",
      "matchup": "DET@SAS",
      "result": "SAS 84, DET 69",
      "round": "Finals",
      "game_num": 1
    },
    {
      "game_id": "0040400177",
      "date": "2005-05-07",
      "matchup": "HOU@DAL",
      "result": "DAL 116, HOU 76",
      "round": "Round 1",
      "game_num": 7
    },
    {
      "game_id": "0040300403",
      "date": "2004-06-10",
      "matchup": "LAL@DET",
      "result": "DET 88, LAL 68",
      "round": "Finals",
      "game_num": 3
    },
    {
      "game_id": "0040300217",
      "date": "2004-05-20",
      "matchup": "NJN@DET",
      "result": "DET 90, NJN 69",
      "round": "Round 2",
      "game_num": 7
    }
  ]
}