{
  "summary": {
    "official_id": "scott-twardoski",
    "name": "Scott Twardoski",
    "slug": "scott-twardoski",
    "raw_ids": [
      "202053",
      "espn:scott-twardoski"
    ],
    "eras": [
      "espn",
      "nba"
    ],
    "first_season": "2009-10",
    "last_season": "2025-26",
    "games_total": 769,
    "games_rs": 762,
    "games_po": 7,
    "games_pi": 0,
    "finals_games": 0,
    "game7s": 0,
    "active": true,
    "per_season": {
      "2009-10": {
        "rs": 5,
        "po": 0,
        "pi": 0,
        "total": 5
      },
      "2010-11": {
        "rs": 6,
        "po": 0,
        "pi": 0,
        "total": 6
      },
      "2011-12": {
        "rs": 38,
        "po": 0,
        "pi": 0,
        "total": 38
      },
      "2012-13": {
        "rs": 53,
        "po": 0,
        "pi": 0,
        "total": 53
      },
      "2013-14": {
        "rs": 49,
        "po": 0,
        "pi": 0,
        "total": 49
      },
      "2014-15": {
        "rs": 56,
        "po": 0,
        "pi": 0,
        "total": 56
      },
      "2015-16": {
        "rs": 50,
        "po": 0,
        "pi": 0,
        "total": 50
      },
      "2016-17": {
        "rs": 42,
        "po": 0,
        "pi": 0,
        "total": 42
      },
      "2017-18": {
        "rs": 52,
        "po": 0,
        "pi": 0,
        "total": 52
      },
      "2018-19": {
        "rs": 58,
        "po": 3,
        "pi": 0,
        "total": 61
      },
      "2019-20": {
        "rs": 51,
        "po": 0,
        "pi": 0,
        "total": 51
      },
      "2020-21": {
        "rs": 41,
        "po": 0,
        "pi": 0,
        "total": 41
      },
      "2021-22": {
        "rs": 49,
        "po": 2,
        "pi": 0,
        "total": 51
      },
      "2022-23": {
        "rs": 44,
        "po": 1,
        "pi": 0,
        "total": 45
      },
      "2023-24": {
        "rs": 60,
        "po": 0,
        "pi": 0,
        "total": 60
      },
      "2024-25": {
        "rs": 52,
        "po": 1,
        "pi": 0,
        "total": 53
      },
      "2025-26": {
        "rs": 56,
        "po": 0,
        "pi": 0,
        "total": 56
      }
    }
  },
  "team_records": [
    {
      "team_abbr": "PHX",
      "games": 76,
      "wins": 37,
      "losses": 39,
      "win_pct": 0.49,
      "home_games": 40,
      "home_wins": 23,
      "avg_margin_for_team": -0.51
    },
    {
      "team_abbr": "LAL",
      "games": 68,
      "wins": 29,
      "losses": 39,
      "win_pct": 0.43,
      "home_games": 39,
      "home_wins": 19,
      "avg_margin_for_team": -2.66
    },
    {
      "team_abbr": "MEM",
      "games": 67,
      "wins": 33,
      "losses": 34,
      "win_pct": 0.49,
      "home_games": 26,
      "home_wins": 19,
      "avg_margin_for_team": 0.19
    },
    {
      "team_abbr": "DEN",
      "games": 62,
      "wins": 34,
      "losses": 28,
      "win_pct": 0.55,
      "home_games": 44,
      "home_wins": 25,
      "avg_margin_for_team": 2.84
    },
    {
      "team_abbr": "LAC",
      "games": 59,
      "wins": 32,
      "losses": 27,
      "win_pct": 0.54,
      "home_games": 36,
      "home_wins": 20,
      "avg_margin_for_team": 2.73
    },
    {
      "team_abbr": "SAC",
      "games": 58,
      "wins": 34,
      "losses": 24,
      "win_pct": 0.59,
      "home_games": 31,
      "home_wins": 24,
      "avg_margin_for_team": 0.86
    },
    {
      "team_abbr": "POR",
      "games": 58,
      "wins": 29,
      "losses": 29,
      "win_pct": 0.5,
      "home_games": 37,
      "home_wins": 20,
      "avg_margin_for_team": 0.71
    },
    {
      "team_abbr": "UTA",
      "games": 58,
      "wins": 28,
      "losses": 30,
      "win_pct": 0.48,
      "home_games": 30,
      "home_wins": 20,
      "avg_margin_for_team": -0.57
    },
    {
      "team_abbr": "GSW",
      "games": 57,
      "wins": 34,
      "losses": 23,
      "win_pct": 0.6,
      "home_games": 33,
      "home_wins": 23,
      "avg_margin_for_team": 1.32
    },
    {
      "team_abbr": "CLE",
      "games": 57,
      "wins": 31,
      "losses": 26,
      "win_pct": 0.54,
      "home_games": 27,
      "home_wins": 16,
      "avg_margin_for_team": 0.21
    },
    {
      "team_abbr": "WAS",
      "games": 56,
      "wins": 21,
      "losses": 35,
      "win_pct": 0.38,
      "home_games": 20,
      "home_wins": 8,
      "avg_margin_for_team": -3.62
    },
    {
      "team_abbr": "NYK",
      "games": 54,
      "wins": 30,
      "losses": 24,
      "win_pct": 0.56,
      "home_games": 28,
      "home_wins": 16,
      "avg_margin_for_team": 3.93
    },
    {
      "team_abbr": "DAL",
      "games": 54,
      "wins": 28,
      "losses": 26,
      "win_pct": 0.52,
      "home_games": 27,
      "home_wins": 15,
      "avg_margin_for_team": -2.02
    },
    {
      "team_abbr": "PHI",
      "games": 52,
      "wins": 28,
      "losses": 24,
      "win_pct": 0.54,
      "home_games": 26,
      "home_wins": 16,
      "avg_margin_for_team": 1.06
    },
    {
      "team_abbr": "MIN",
      "games": 51,
      "wins": 22,
      "losses": 29,
      "win_pct": 0.43,
      "home_games": 21,
      "home_wins": 14,
      "avg_margin_for_team": -0.59
    },
    {
      "team_abbr": "TOR",
      "games": 49,
      "wins": 25,
      "losses": 24,
      "win_pct": 0.51,
      "home_games": 21,
      "home_wins": 13,
      "avg_margin_for_team": 2.67
    },
    {
      "team_abbr": "ATL",
      "games": 48,
      "wins": 22,
      "losses": 26,
      "win_pct": 0.46,
      "home_games": 21,
      "home_wins": 13,
      "avg_margin_for_team": -0.27
    },
    {
      "team_abbr": "MIL",
      "games": 46,
      "wins": 29,
      "losses": 17,
      "win_pct": 0.63,
      "home_games": 26,
      "home_wins": 19,
      "avg_margin_for_team": 3.7
    },
    {
      "team_abbr": "BOS",
      "games": 45,
      "wins": 32,
      "losses": 13,
      "win_pct": 0.71,
      "home_games": 24,
      "home_wins": 20,
      "avg_margin_for_team": 6.93
    },
    {
      "team_abbr": "ORL",
      "games": 45,
      "wins": 9,
      "losses": 36,
      "win_pct": 0.2,
      "home_games": 19,
      "home_wins": 5,
      "avg_margin_for_team": -11.87
    },
    {
      "team_abbr": "CHI",
      "games": 43,
      "wins": 23,
      "losses": 20,
      "win_pct": 0.53,
      "home_games": 22,
      "home_wins": 13,
      "avg_margin_for_team": 0.53
    },
    {
      "team_abbr": "BKN",
      "games": 43,
      "wins": 16,
      "losses": 27,
      "win_pct": 0.37,
      "home_games": 24,
      "home_wins": 11,
      "avg_margin_for_team": -2.91
    },
    {
      "team_abbr": "DET",
      "games": 42,
      "wins": 13,
      "losses": 29,
      "win_pct": 0.31,
      "home_games": 17,
      "home_wins": 6,
      "avg_margin_for_team": -8.4
    },
    {
      "team_abbr": "CHA",
      "games": 42,
      "wins": 17,
      "losses": 25,
      "win_pct": 0.4,
      "home_games": 21,
      "home_wins": 9,
      "avg_margin_for_team": -0.57
    },
    {
      "team_abbr": "SAS",
      "games": 42,
      "wins": 29,
      "losses": 13,
      "win_pct": 0.69,
      "home_games": 16,
      "home_wins": 14,
      "avg_margin_for_team": 5.52
    },
    {
      "team_abbr": "OKC",
      "games": 41,
      "wins": 27,
      "losses": 14,
      "win_pct": 0.66,
      "home_games": 17,
      "home_wins": 14,
      "avg_margin_for_team": 4.63
    },
    {
      "team_abbr": "NOP",
      "games": 41,
      "wins": 12,
      "losses": 29,
      "win_pct": 0.29,
      "home_games": 19,
      "home_wins": 7,
      "avg_margin_for_team": -5.29
    },
    {
      "team_abbr": "IND",
      "games": 40,
      "wins": 22,
      "losses": 18,
      "win_pct": 0.55,
      "home_games": 18,
      "home_wins": 14,
      "avg_margin_for_team": 1.48
    },
    {
      "team_abbr": "MIA",
      "games": 38,
      "wins": 23,
      "losses": 15,
      "win_pct": 0.61,
      "home_games": 13,
      "home_wins": 9,
      "avg_margin_for_team": 3.82
    },
    {
      "team_abbr": "HOU",
      "games": 38,
      "wins": 16,
      "losses": 22,
      "win_pct": 0.42,
      "home_games": 22,
      "home_wins": 11,
      "avg_margin_for_team": -3.87
    },
    {
      "team_abbr": "NJN",
      "games": 5,
      "wins": 3,
      "losses": 2,
      "win_pct": 0.6,
      "home_games": 2,
      "home_wins": 2,
      "avg_margin_for_team": -5.4
    },
    {
      "team_abbr": "NOH",
      "games": 3,
      "wins": 1,
      "losses": 2,
      "win_pct": 0.33,
      "home_games": 2,
      "home_wins": 0,
      "avg_margin_for_team": -7.33
    }
  ],
  "whistle_profile": {
    "rs": {
      "n": 762,
      "n_boxscore": 762,
      "avg_total_points": 214.76,
      "avg_total_fta": 45.07,
      "avg_total_pf": 39.81,
      "home_win_pct": 0.6,
      "avg_abs_margin": 11.96,
      "ot_games": 46,
      "ot_rate": 0.06
    },
    "po": {
      "n": 7,
      "n_boxscore": 7,
      "avg_total_points": 203.71,
      "avg_total_fta": 48.71,
      "avg_total_pf": 43.86,
      "home_win_pct": 0.43,
      "avg_abs_margin": 16.0,
      "ot_games": 0,
      "ot_rate": 0.0
    }
  },
  "top_performances": [
    {
      "player_name": "Damian Lillard",
      "pts": 60,
      "team_abbr": "POR",
      "opp_abbr": "BKN",
      "game_date": "2019-11-08",
      "game_id": "0021900125",
      "player_slug": "damian-lillard"
    },
    {
      "player_name": "Nikola Jokic",
      "pts": 56,
      "team_abbr": "DEN",
      "opp_abbr": "MIN",
      "game_date": "2025-12-26",
      "game_id": "401809242",
      "player_slug": "nikola-jokic"
    },
    {
      "player_name": "Anthony Davis",
      "pts": 55,
      "team_abbr": "LAL",
      "opp_abbr": "WAS",
      "game_date": "2022-12-04",
      "game_id": "0022200349",
      "player_slug": "anthony-davis"
    },
    {
      "player_name": "Jayson Tatum",
      "pts": 53,
      "team_abbr": "BOS",
      "opp_abbr": "MIN",
      "game_date": "2021-04-09",
      "game_id": "0022000792",
      "player_slug": "jayson-tatum"
    },
    {
      "player_name": "Stephen Curry",
      "pts": 51,
      "team_abbr": "GSW",
      "opp_abbr": "WAS",
      "game_date": "2018-10-24",
      "game_id": "0021800062",
      "player_slug": "stephen-curry"
    },
    {
      "player_name": "Lauri Markkanen",
      "pts": 51,
      "team_abbr": "UTA",
      "opp_abbr": "PHX",
      "game_date": "2025-10-28",
      "game_id": "401809975",
      "player_slug": "lauri-markkanen"
    },
    {
      "player_name": "Damian Lillard",
      "pts": 50,
      "team_abbr": "POR",
      "opp_abbr": "SAC",
      "game_date": "2018-02-09",
      "game_id": "0021700825",
      "player_slug": "damian-lillard"
    },
    {
      "player_name": "Giannis Antetokounmpo",
      "pts": 50,
      "team_abbr": "MIL",
      "opp_abbr": "IND",
      "game_date": "2022-02-15",
      "game_id": "0022100870",
      "player_slug": "giannis-antetokounmpo"
    },
    {
      "player_name": "Jalen Brunson",
      "pts": 50,
      "team_abbr": "NYK",
      "opp_abbr": "PHX",
      "game_date": "2023-12-16",
      "game_id": "401584961",
      "player_slug": "jalen-brunson"
    },
    {
      "player_name": "Devin Booker",
      "pts": 48,
      "team_abbr": "PHX",
      "opp_abbr": "MEM",
      "game_date": "2019-03-30",
      "game_id": "0021801144",
      "player_slug": "devin-booker"
    },
    {
      "player_name": "Paul George",
      "pts": 47,
      "team_abbr": "OKC",
      "opp_abbr": "POR",
      "game_date": "2019-02-11",
      "game_id": "0021800846",
      "player_slug": "paul-george"
    },
    {
      "player_name": "Lauri Markkanen",
      "pts": 47,
      "team_abbr": "UTA",
      "opp_abbr": "CHI",
      "game_date": "2025-11-17",
      "game_id": "401810095",
      "player_slug": "lauri-markkanen"
    },
    {
      "player_name": "Pau Gasol",
      "pts": 46,
      "team_abbr": "CHI",
      "opp_abbr": "MIL",
      "game_date": "2015-01-10",
      "game_id": "0021400554",
      "player_slug": "pau-gasol"
    },
    {
      "player_name": "James Harden",
      "pts": 46,
      "team_abbr": "HOU",
      "opp_abbr": "OKC",
      "game_date": "2013-02-21",
      "game_id": "400278524",
      "player_slug": "james-harden"
    },
    {
      "player_name": "Kawhi Leonard",
      "pts": 45,
      "team_abbr": "TOR",
      "opp_abbr": "UTA",
      "game_date": "2019-01-01",
      "game_id": "0021800549",
      "player_slug": "kawhi-leonard"
    },
    {
      "player_name": "Luka Doncic",
      "pts": 45,
      "team_abbr": "DAL",
      "opp_abbr": "LAC",
      "game_date": "2022-02-12",
      "game_id": "0022100853",
      "player_slug": "luka-doncic"
    },
    {
      "player_name": "Damian Lillard",
      "pts": 45,
      "team_abbr": "MIL",
      "opp_abbr": "DET",
      "game_date": "2024-01-20",
      "game_id": "401585220",
      "player_slug": "damian-lillard"
    },
    {
      "player_name": "Jamal Murray",
      "pts": 45,
      "team_abbr": "DEN",
      "opp_abbr": "DAL",
      "game_date": "2025-01-15",
      "game_id": "401705125",
      "player_slug": "jamal-murray"
    },
    {
      "player_name": "Carmelo Anthony",
      "pts": 44,
      "team_abbr": "NYK",
      "opp_abbr": "DAL",
      "game_date": "2014-02-24",
      "game_id": "0021300843",
      "player_slug": "carmelo-anthony"
    },
    {
      "player_name": "Bojan Bogdanovic",
      "pts": 44,
      "team_abbr": "BKN",
      "opp_abbr": "PHI",
      "game_date": "2016-03-15",
      "game_id": "0021500999",
      "player_slug": "bojan-bogdanovic"
    },
    {
      "player_name": "Giannis Antetokounmpo",
      "pts": 44,
      "team_abbr": "MIL",
      "opp_abbr": "LAL",
      "game_date": "2022-02-08",
      "game_id": "0022100822",
      "player_slug": "giannis-antetokounmpo"
    },
    {
      "player_name": "De'Aaron Fox",
      "pts": 44,
      "team_abbr": "SAC",
      "opp_abbr": "LAL",
      "game_date": "2024-03-07",
      "game_id": "401585529",
      "player_slug": "deaaron-fox"
    },
    {
      "player_name": "Anthony Edwards",
      "pts": 44,
      "team_abbr": "MIN",
      "opp_abbr": "PHX",
      "game_date": "2025-03-03",
      "game_id": "401705439",
      "player_slug": "anthony-edwards"
    },
    {
      "player_name": "Anthony Edwards",
      "pts": 44,
      "team_abbr": "MIN",
      "opp_abbr": "DEN",
      "game_date": "2025-12-26",
      "game_id": "401809242",
      "player_slug": "anthony-edwards"
    },
    {
      "player_name": "Anthony Davis",
      "pts": 43,
      "team_abbr": "NOP",
      "opp_abbr": "ATL",
      "game_date": "2015-11-06",
      "game_id": "0021500081",
      "player_slug": "anthony-davis"
    }
  ],
  "player_swings": [
    {
      "player_id": "202703",
      "name": "Nikola Mirotic",
      "n_games": 17,
      "slug": "nikola-mirotic",
      "pts_with_ref": 15.18,
      "pts_baseline": 11.65,
      "pts_swing": 3.53,
      "fta_swing": -0.06,
      "pf_swing": -0.17
    },
    {
      "player_id": "203933",
      "name": "T.J. Warren",
      "n_games": 20,
      "slug": "t-j-warren",
      "pts_with_ref": 11.45,
      "pts_baseline": 14.57,
      "pts_swing": -3.12,
      "fta_swing": 0.82,
      "pf_swing": -0.94
    },
    {
      "player_id": "1626144",
      "name": "Emmanuel Mudiay",
      "n_games": 15,
      "slug": "emmanuel-mudiay",
      "pts_with_ref": 15.0,
      "pts_baseline": 11.9,
      "pts_swing": 3.1,
      "fta_swing": 0.02,
      "pf_swing": 0.27
    },
    {
      "player_id": "4066387",
      "name": "Amir Coffey",
      "n_games": 18,
      "slug": "amir-coffey",
      "pts_with_ref": 10.61,
      "pts_baseline": 7.56,
      "pts_swing": 3.05,
      "fta_swing": 0.58,
      "pf_swing": 0.15
    },
    {
      "player_id": "2747",
      "name": "JR Smith",
      "n_games": 22,
      "slug": "jr-smith",
      "pts_with_ref": 14.5,
      "pts_baseline": 11.54,
      "pts_swing": 2.96,
      "fta_swing": 0.78,
      "pf_swing": -0.2
    },
    {
      "player_id": "201945",
      "name": "Gerald Henderson",
      "n_games": 20,
      "slug": "gerald-henderson",
      "pts_with_ref": 9.1,
      "pts_baseline": 11.92,
      "pts_swing": -2.82,
      "fta_swing": -0.51,
      "pf_swing": -0.32
    },
    {
      "player_id": "201167",
      "name": "Arron Afflalo",
      "n_games": 18,
      "slug": "arron-afflalo",
      "pts_with_ref": 10.33,
      "pts_baseline": 13.12,
      "pts_swing": -2.79,
      "fta_swing": -0.87,
      "pf_swing": -0.09
    },
    {
      "player_id": "1630162",
      "name": "Anthony Edwards",
      "n_games": 20,
      "slug": "anthony-edwards",
      "pts_with_ref": 27.05,
      "pts_baseline": 24.27,
      "pts_swing": 2.78,
      "fta_swing": 1.31,
      "pf_swing": 0.13
    },
    {
      "player_id": "203085",
      "name": "Austin Rivers",
      "n_games": 24,
      "slug": "austin-rivers",
      "pts_with_ref": 4.5,
      "pts_baseline": 7.27,
      "pts_swing": -2.77,
      "fta_swing": -0.12,
      "pf_swing": 0.1
    },
    {
      "player_id": "203954",
      "name": "Joel Embiid",
      "n_games": 20,
      "slug": "joel-embiid",
      "pts_with_ref": 25.05,
      "pts_baseline": 27.79,
      "pts_swing": -2.74,
      "fta_swing": -0.31,
      "pf_swing": 0.02
    },
    {
      "player_id": "1626163",
      "name": "Frank Kaminsky",
      "n_games": 19,
      "slug": "frank-kaminsky",
      "pts_with_ref": 12.0,
      "pts_baseline": 9.34,
      "pts_swing": 2.66,
      "fta_swing": 0.56,
      "pf_swing": 0.21
    },
    {
      "player_id": "202714",
      "name": "Shelvin Mack",
      "n_games": 16,
      "slug": "shelvin-mack",
      "pts_with_ref": 9.44,
      "pts_baseline": 6.83,
      "pts_swing": 2.61,
      "fta_swing": -0.09,
      "pf_swing": 0.13
    },
    {
      "player_id": "101123",
      "name": "Gerald Green",
      "n_games": 23,
      "slug": "gerald-green",
      "pts_with_ref": 14.91,
      "pts_baseline": 12.3,
      "pts_swing": 2.61,
      "fta_swing": 0.22,
      "pf_swing": 0.65
    },
    {
      "player_id": "1628436",
      "name": "Luke Kornet",
      "n_games": 21,
      "slug": "luke-kornet",
      "pts_with_ref": 3.19,
      "pts_baseline": 5.81,
      "pts_swing": -2.61,
      "fta_swing": -0.39,
      "pf_swing": -0.2
    },
    {
      "player_id": "201145",
      "name": "Jeff Green",
      "n_games": 44,
      "slug": "jeff-green",
      "pts_with_ref": 8.32,
      "pts_baseline": 10.89,
      "pts_swing": -2.57,
      "fta_swing": -0.83,
      "pf_swing": -0.04
    },
    {
      "player_id": "1629630",
      "name": "Ja Morant",
      "n_games": 16,
      "slug": "ja-morant",
      "pts_with_ref": 20.94,
      "pts_baseline": 23.49,
      "pts_swing": -2.55,
      "fta_swing": 0.68,
      "pf_swing": 0.14
    },
    {
      "player_id": "203468",
      "name": "CJ McCollum",
      "n_games": 47,
      "slug": "cj-mccollum",
      "pts_with_ref": 17.38,
      "pts_baseline": 19.9,
      "pts_swing": -2.52,
      "fta_swing": -0.28,
      "pf_swing": 0.0
    },
    {
      "player_id": "201977",
      "name": "Marcus Thornton",
      "n_games": 19,
      "slug": "marcus-thornton",
      "pts_with_ref": 14.58,
      "pts_baseline": 12.07,
      "pts_swing": 2.51,
      "fta_swing": 0.49,
      "pf_swing": 0.03
    },
    {
      "player_id": "1628988",
      "name": "Aaron Holiday",
      "n_games": 19,
      "slug": "aaron-holiday",
      "pts_with_ref": 9.42,
      "pts_baseline": 6.94,
      "pts_swing": 2.49,
      "fta_swing": 0.34,
      "pf_swing": 0.18
    },
    {
      "player_id": "1629018",
      "name": "Gary Trent Jr.",
      "n_games": 15,
      "slug": "gary-trent-jr",
      "pts_with_ref": 14.53,
      "pts_baseline": 12.08,
      "pts_swing": 2.45,
      "fta_swing": -0.69,
      "pf_swing": 0.38
    },
    {
      "player_id": "1628422",
      "name": "Damyean Dotson",
      "n_games": 17,
      "slug": "damyean-dotson",
      "pts_with_ref": 5.53,
      "pts_baseline": 7.95,
      "pts_swing": -2.42,
      "fta_swing": 0.23,
      "pf_swing": -0.12
    },
    {
      "player_id": "1628384",
      "name": "OG Anunoby",
      "n_games": 18,
      "slug": "og-anunoby",
      "pts_with_ref": 8.83,
      "pts_baseline": 11.24,
      "pts_swing": -2.4,
      "fta_swing": -0.02,
      "pf_swing": 0.19
    },
    {
      "player_id": "201988",
      "name": "Patty Mills",
      "n_games": 32,
      "slug": "patty-mills",
      "pts_with_ref": 6.25,
      "pts_baseline": 8.63,
      "pts_swing": -2.38,
      "fta_swing": -0.59,
      "pf_swing": -0.22
    },
    {
      "player_id": "2225",
      "name": "Tony Parker",
      "n_games": 17,
      "slug": "tony-parker",
      "pts_with_ref": 16.12,
      "pts_baseline": 13.75,
      "pts_swing": 2.37,
      "fta_swing": 0.0,
      "pf_swing": -0.04
    },
    {
      "player_id": "1626246",
      "name": "Boban Marjanovic",
      "n_games": 17,
      "slug": "boban-marjanovic",
      "pts_with_ref": 8.12,
      "pts_baseline": 5.76,
      "pts_swing": 2.35,
      "fta_swing": 0.43,
      "pf_swing": -0.13
    },
    {
      "player_id": "1627742",
      "name": "Brandon Ingram",
      "n_games": 24,
      "slug": "brandon-ingram",
      "pts_with_ref": 16.33,
      "pts_baseline": 18.67,
      "pts_swing": -2.34,
      "fta_swing": -0.62,
      "pf_swing": 0.28
    },
    {
      "player_id": "4066259",
      "name": "De'Aaron Fox",
      "n_games": 27,
      "slug": "deaaron-fox",
      "pts_with_ref": 22.96,
      "pts_baseline": 20.64,
      "pts_swing": 2.32,
      "fta_swing": 0.33,
      "pf_swing": -0.02
    },
    {
      "player_id": "203922",
      "name": "Glenn Robinson III",
      "n_games": 16,
      "slug": "glenn-robinson-iii",
      "pts_with_ref": 3.75,
      "pts_baseline": 5.99,
      "pts_swing": -2.24,
      "fta_swing": -0.05,
      "pf_swing": 0.01
    },
    {
      "player_id": "203487",
      "name": "Michael Carter-Williams",
      "n_games": 15,
      "slug": "michael-carter-williams",
      "pts_with_ref": 9.27,
      "pts_baseline": 11.48,
      "pts_swing": -2.22,
      "fta_swing": -1.26,
      "pf_swing": -0.16
    },
    {
      "player_id": "201956",
      "name": "Omri Casspi",
      "n_games": 24,
      "slug": "omri-casspi",
      "pts_with_ref": 10.21,
      "pts_baseline": 8.01,
      "pts_swing": 2.2,
      "fta_swing": 0.6,
      "pf_swing": 0.05
    },
    {
      "player_id": "202323",
      "name": "Evan Turner",
      "n_games": 26,
      "slug": "evan-turner",
      "pts_with_ref": 11.19,
      "pts_baseline": 9.01,
      "pts_swing": 2.18,
      "fta_swing": 0.38,
      "pf_swing": -0.61
    },
    {
      "player_id": "1629632",
      "name": "Coby White",
      "n_games": 19,
      "slug": "coby-white",
      "pts_with_ref": 13.11,
      "pts_baseline": 15.29,
      "pts_swing": -2.18,
      "fta_swing": 0.45,
      "pf_swing": -0.18
    },
    {
      "player_id": "1630178",
      "name": "Tyrese Maxey",
      "n_games": 17,
      "slug": "tyrese-maxey",
      "pts_with_ref": 21.18,
      "pts_baseline": 19.05,
      "pts_swing": 2.12,
      "fta_swing": 0.4,
      "pf_swing": 0.05
    },
    {
      "player_id": "202689",
      "name": "Kemba Walker",
      "n_games": 31,
      "slug": "kemba-walker",
      "pts_with_ref": 16.58,
      "pts_baseline": 18.69,
      "pts_swing": -2.11,
      "fta_swing": -0.16,
      "pf_swing": 0.41
    },
    {
      "player_id": "202322",
      "name": "John Wall",
      "n_games": 27,
      "slug": "john-wall",
      "pts_with_ref": 16.19,
      "pts_baseline": 18.27,
      "pts_swing": -2.09,
      "fta_swing": -0.01,
      "pf_swing": -0.28
    },
    {
      "player_id": "201581",
      "name": "JJ Hickson",
      "n_games": 16,
      "slug": "jj-hickson",
      "pts_with_ref": 12.0,
      "pts_baseline": 9.92,
      "pts_swing": 2.08,
      "fta_swing": 2.15,
      "pf_swing": 0.23
    },
    {
      "player_id": "1626196",
      "name": "Josh Richardson",
      "n_games": 18,
      "slug": "josh-richardson",
      "pts_with_ref": 8.89,
      "pts_baseline": 10.95,
      "pts_swing": -2.06,
      "fta_swing": 0.15,
      "pf_swing": -0.52
    },
    {
      "player_id": "101181",
      "name": "Jose Calderon",
      "n_games": 24,
      "slug": "jose-calderon",
      "pts_with_ref": 10.29,
      "pts_baseline": 8.25,
      "pts_swing": 2.05,
      "fta_swing": 0.52,
      "pf_swing": -0.0
    },
    {
      "player_id": "203081",
      "name": "Damian Lillard",
      "n_games": 45,
      "slug": "damian-lillard",
      "pts_with_ref": 27.47,
      "pts_baseline": 25.41,
      "pts_swing": 2.05,
      "fta_swing": 0.47,
      "pf_swing": 0.05
    },
    {
      "player_id": "1629659",
      "name": "Talen Horton-Tucker",
      "n_games": 19,
      "slug": "talen-horton-tucker",
      "pts_with_ref": 7.53,
      "pts_baseline": 9.58,
      "pts_swing": -2.05,
      "fta_swing": 0.2,
      "pf_swing": -0.43
    },
    {
      "player_id": "202696",
      "name": "Nikola Vucevic",
      "n_games": 41,
      "slug": "nikola-vucevic",
      "pts_with_ref": 14.78,
      "pts_baseline": 16.83,
      "pts_swing": -2.04,
      "fta_swing": -0.74,
      "pf_swing": -0.09
    },
    {
      "player_id": "203925",
      "name": "Joe Harris",
      "n_games": 18,
      "slug": "joe-harris",
      "pts_with_ref": 8.94,
      "pts_baseline": 10.98,
      "pts_swing": -2.04,
      "fta_swing": -0.16,
      "pf_swing": -0.49
    },
    {
      "player_id": "1628401",
      "name": "Derrick White",
      "n_games": 24,
      "slug": "derrick-white",
      "pts_with_ref": 16.0,
      "pts_baseline": 13.97,
      "pts_swing": 2.03,
      "fta_swing": -0.29,
      "pf_swing": -0.09
    },
    {
      "player_id": "203087",
      "name": "Jeremy Lamb",
      "n_games": 18,
      "slug": "jeremy-lamb",
      "pts_with_ref": 8.28,
      "pts_baseline": 10.3,
      "pts_swing": -2.02,
      "fta_swing": 0.06,
      "pf_swing": -0.46
    },
    {
      "player_id": "1626158",
      "name": "Richaun Holmes",
      "n_games": 18,
      "slug": "richaun-holmes",
      "pts_with_ref": 9.72,
      "pts_baseline": 7.71,
      "pts_swing": 2.01,
      "fta_swing": 0.43,
      "pf_swing": -0.07
    },
    {
      "player_id": "203463",
      "name": "Ben McLemore",
      "n_games": 22,
      "slug": "ben-mclemore",
      "pts_with_ref": 10.64,
      "pts_baseline": 8.65,
      "pts_swing": 1.99,
      "fta_swing": 0.51,
      "pf_swing": -0.01
    },
    {
      "player_id": "1626209",
      "name": "Mario Hezonja",
      "n_games": 17,
      "slug": "mario-hezonja",
      "pts_with_ref": 8.94,
      "pts_baseline": 6.98,
      "pts_swing": 1.97,
      "fta_swing": 0.41,
      "pf_swing": 0.07
    },
    {
      "player_id": "201569",
      "name": "Eric Gordon",
      "n_games": 35,
      "slug": "eric-gordon",
      "pts_with_ref": 11.74,
      "pts_baseline": 13.68,
      "pts_swing": -1.94,
      "fta_swing": -0.68,
      "pf_swing": 0.12
    },
    {
      "player_id": "203476",
      "name": "Gorgui Dieng",
      "n_games": 18,
      "slug": "gorgui-dieng",
      "pts_with_ref": 9.78,
      "pts_baseline": 7.84,
      "pts_swing": 1.94,
      "fta_swing": 0.19,
      "pf_swing": 0.19
    },
    {
      "player_id": "2571",
      "name": "Leandro Barbosa",
      "n_games": 15,
      "slug": "leandro-barbosa",
      "pts_with_ref": 5.8,
      "pts_baseline": 7.73,
      "pts_swing": -1.93,
      "fta_swing": -0.64,
      "pf_swing": 0.43
    }
  ],
  "notable_games": []
}