{
  "summary": {
    "name": "Amen Thompson",
    "slug": "amen-thompson",
    "first_season": "2023-24",
    "last_season": "2025-26",
    "teams": [
      "HOU"
    ],
    "games_total": 223,
    "eras": [
      "espn"
    ]
  },
  "ref_splits": [
    {
      "ref_name": "Brian Forte",
      "ref_slug": "brian-forte",
      "player_id": "4684740",
      "n_games": 15,
      "pts_with_ref": 14.07,
      "pts_baseline": 13.66,
      "pts_swing": 0.41,
      "reb_with_ref": 7.2,
      "reb_baseline": 7.41,
      "reb_swing": -0.21,
      "ast_with_ref": 3.8,
      "ast_baseline": 3.85,
      "ast_swing": -0.05,
      "seasons": [
        "2023-24",
        "2024-25",
        "2025-26"
      ]
    },
    {
      "ref_name": "Sean Wright",
      "ref_slug": "sean-wright",
      "player_id": "4684740",
      "n_games": 15,
      "pts_with_ref": 15.93,
      "pts_baseline": 14.95,
      "pts_swing": 0.98,
      "reb_with_ref": 8.2,
      "reb_baseline": 7.61,
      "reb_swing": 0.59,
      "ast_with_ref": 4.33,
      "ast_baseline": 4.15,
      "ast_swing": 0.18,
      "seasons": [
        "2023-24",
        "2024-25",
        "2025-26"
      ]
    }
  ],
  "top_games": [
    {
      "pts": 41,
      "reb": 9,
      "ast": 7,
      "team_abbr": "HOU",
      "opp_abbr": "MIN",
      "game_date": "2026-04-11",
      "game_id": "401811033",
      "crew": [
        {
          "name": "Jason Goldenberg",
          "slug": "jason-goldenberg"
        },
        {
          "name": "Ben Taylor",
          "slug": "ben-taylor"
        },
        {
          "name": "Sha'Rae Mitchell",
          "slug": "sharae-mitchell"
        }
      ]
    },
    {
      "pts": 33,
      "reb": 9,
      "ast": 4,
      "team_abbr": "HOU",
      "opp_abbr": "BOS",
      "game_date": "2025-01-28",
      "game_id": "401705216",
      "crew": [
        {
          "name": "Derrick Collins",
          "slug": "derrick-collins"
        },
        {
          "name": "Tyler Ford",
          "slug": "tyler-ford"
        },
        {
          "name": "Suyash Mehta",
          "slug": "suyash-mehta"
        }
      ]
    },
    {
      "pts": 31,
      "reb": 4,
      "ast": 1,
      "team_abbr": "HOU",
      "opp_abbr": "PHX",
      "game_date": "2025-12-06",
      "game_id": "401810201",
      "crew": [
        {
          "name": "Derrick Collins",
          "slug": "derrick-collins"
        },
        {
          "name": "Jacyn Goble",
          "slug": "jacyn-goble"
        },
        {
          "name": "Mitchell Ervin",
          "slug": "mitchell-ervin"
        }
      ]
    },
    {
      "pts": 31,
      "reb": 13,
      "ast": 6,
      "team_abbr": "HOU",
      "opp_abbr": "SAC",
      "game_date": "2026-01-12",
      "game_id": "401810412",
      "crew": [
        {
          "name": "John Goble",
          "slug": "john-goble"
        },
        {
          "name": "Ashley Moyer-Gleich",
          "slug": "ashley-moyer-gleich"
        },
        {
          "name": "Dannica Baroody",
          "slug": "dannica-baroody"
        }
      ]
    },
    {
      "pts": 28,
      "reb": 10,
      "ast": 7,
      "team_abbr": "HOU",
      "opp_abbr": "MEM",
      "game_date": "2025-11-06",
      "game_id": "401810031",
      "crew": [
        {
          "name": "James Capers",
          "slug": "james-capers"
        },
        {
          "name": "Natalie Sago",
          "slug": "natalie-sago"
        },
        {
          "name": "JD Ralls",
          "slug": "jd-ralls"
        }
      ]
    },
    {
      "pts": 28,
      "reb": 7,
      "ast": 8,
      "team_abbr": "HOU",
      "opp_abbr": "PHX",
      "game_date": "2025-11-25",
      "game_id": "401810145",
      "crew": [
        {
          "name": "Tre Maddox",
          "slug": "tre-maddox"
        },
        {
          "name": "Brett Nansel",
          "slug": "brett-nansel"
        },
        {
          "name": "Scott Twardoski",
          "slug": "scott-twardoski"
        }
      ]
    },
    {
      "pts": 27,
      "reb": 5,
      "ast": 4,
      "team_abbr": "HOU",
      "opp_abbr": "DAL",
      "game_date": "2025-11-04",
      "game_id": "401810015",
      "crew": [
        {
          "name": "Jacyn Goble",
          "slug": "jacyn-goble"
        },
        {
          "name": "Mitchell Ervin",
          "slug": "mitchell-ervin"
        },
        {
          "name": "Pat O'Connell",
          "slug": "pat-oconnell"
        }
      ]
    },
    {
      "pts": 26,
      "reb": 11,
      "ast": 4,
      "team_abbr": "HOU",
      "opp_abbr": "LAL",
      "game_date": "2026-04-25",
      "game_id": "401869400",
      "crew": [
        {
          "name": "Zach Zarba",
          "slug": "zach-zarba"
        },
        {
          "name": "Tre Maddox",
          "slug": "tre-maddox"
        },
        {
          "name": "Nate Green",
          "slug": "nate-green"
        }
      ]
    },
    {
      "pts": 26,
      "reb": 11,
      "ast": 4,
      "team_abbr": "HOU",
      "opp_abbr": "LAL",
      "game_date": "2026-03-19",
      "game_id": "401810862",
      "crew": [
        {
          "name": "Brent Barnaky",
          "slug": "brent-barnaky"
        },
        {
          "name": "Sean Wright",
          "slug": "sean-wright"
        },
        {
          "name": "Mousa Dagher",
          "slug": "mousa-dagher"
        }
      ]
    },
    {
      "pts": 26,
      "reb": 7,
      "ast": 7,
      "team_abbr": "HOU",
      "opp_abbr": "POR",
      "game_date": "2026-03-07",
      "game_id": "401810765",
      "crew": [
        {
          "name": "Josh Tiven",
          "slug": "josh-tiven"
        },
        {
          "name": "Mark Lindsay",
          "slug": "mark-lindsay"
        },
        {
          "name": "Matt Myers",
          "slug": "matt-myers"
        }
      ]
    }
  ]
}