{
  "summary": {
    "name": "Chris Quinn",
    "slug": "chris-quinn",
    "first_season": "2006-07",
    "last_season": "2012-13",
    "teams": [
      "CLE",
      "MIA",
      "NJN",
      "SAS"
    ],
    "games_total": 246,
    "eras": [
      "espn",
      "nba"
    ]
  },
  "ref_splits": [
    {
      "ref_name": "Bill Kennedy",
      "ref_slug": "bill-kennedy",
      "player_id": "200809",
      "n_games": 18,
      "pts_with_ref": 2.17,
      "pts_baseline": 4.04,
      "pts_swing": -1.88,
      "reb_with_ref": 0.83,
      "reb_baseline": 0.97,
      "reb_swing": -0.14,
      "ast_with_ref": 0.67,
      "ast_baseline": 1.77,
      "ast_swing": -1.1,
      "seasons": [
        "2006-07",
        "2007-08",
        "2008-09",
        "2009-10",
        "2010-11",
        "2012-13"
      ]
    },
    {
      "ref_name": "Derrick Stafford",
      "ref_slug": "derrick-stafford",
      "player_id": "200809",
      "n_games": 16,
      "pts_with_ref": 3.38,
      "pts_baseline": 4.05,
      "pts_swing": -0.67,
      "reb_with_ref": 0.62,
      "reb_baseline": 0.97,
      "reb_swing": -0.35,
      "ast_with_ref": 1.12,
      "ast_baseline": 1.71,
      "ast_swing": -0.59,
      "seasons": [
        "2006-07",
        "2007-08",
        "2008-09",
        "2009-10",
        "2010-11"
      ]
    },
    {
      "ref_name": "Scott Foster",
      "ref_slug": "scott-foster",
      "player_id": "200809",
      "n_games": 16,
      "pts_with_ref": 4.44,
      "pts_baseline": 5.18,
      "pts_swing": -0.74,
      "reb_with_ref": 1.56,
      "reb_baseline": 1.29,
      "reb_swing": 0.27,
      "ast_with_ref": 3.0,
      "ast_baseline": 2.12,
      "ast_swing": 0.88,
      "seasons": [
        "2006-07",
        "2007-08",
        "2008-09",
        "2009-10",
        "2010-11",
        "2012-13"
      ]
    },
    {
      "ref_name": "James Capers",
      "ref_slug": "james-capers",
      "player_id": "200809",
      "n_games": 15,
      "pts_with_ref": 4.33,
      "pts_baseline": 4.79,
      "pts_swing": -0.46,
      "reb_with_ref": 1.07,
      "reb_baseline": 1.16,
      "reb_swing": -0.1,
      "ast_with_ref": 2.13,
      "ast_baseline": 1.99,
      "ast_swing": 0.14,
      "seasons": [
        "2006-07",
        "2007-08",
        "2008-09",
        "2009-10",
        "2010-11",
        "2012-13"
      ]
    },
    {
      "ref_name": "Rodney Mott",
      "ref_slug": "rodney-mott",
      "player_id": "200809",
      "n_games": 15,
      "pts_with_ref": 4.27,
      "pts_baseline": 4.25,
      "pts_swing": 0.02,
      "reb_with_ref": 1.73,
      "reb_baseline": 1.07,
      "reb_swing": 0.67,
      "ast_with_ref": 2.4,
      "ast_baseline": 1.8,
      "ast_swing": 0.6,
      "seasons": [
        "2006-07",
        "2007-08",
        "2008-09",
        "2009-10",
        "2010-11"
      ]
    },
    {
      "ref_name": "Tom Washington",
      "ref_slug": "tom-washington",
      "player_id": "200809",
      "n_games": 15,
      "pts_with_ref": 2.13,
      "pts_baseline": 3.82,
      "pts_swing": -1.68,
      "reb_with_ref": 0.47,
      "reb_baseline": 0.93,
      "reb_swing": -0.47,
      "ast_with_ref": 1.27,
      "ast_baseline": 1.65,
      "ast_swing": -0.39,
      "seasons": [
        "2006-07",
        "2007-08",
        "2008-09",
        "2009-10",
        "2010-11"
      ]
    }
  ],
  "top_games": [
    {
      "pts": 26,
      "reb": 4,
      "ast": 5,
      "team_abbr": "MIA",
      "opp_abbr": "DET",
      "game_date": "2009-04-15",
      "game_id": "0020801223",
      "crew": [
        {
          "name": "Derrick Collins",
          "slug": "derrick-collins"
        },
        {
          "name": "Jimmy Clark",
          "slug": "jimmy-clark"
        },
        {
          "name": "Mark Wunderlich",
          "slug": "mark-wunderlich"
        }
      ]
    },
    {
      "pts": 24,
      "reb": 4,
      "ast": 4,
      "team_abbr": "MIA",
      "opp_abbr": "MIL",
      "game_date": "2008-03-24",
      "game_id": "0020701046",
      "crew": [
        {
          "name": "Eli Roe",
          "slug": "eli-roe"
        },
        {
          "name": "Phil Robinson",
          "slug": "phil-robinson"
        },
        {
          "name": "Monty McCutchen",
          "slug": "monty-mccutchen"
        }
      ]
    },
    {
      "pts": 24,
      "reb": 2,
      "ast": 8,
      "team_abbr": "MIA",
      "opp_abbr": "WAS",
      "game_date": "2008-04-04",
      "game_id": "0020701128",
      "crew": [
        {
          "name": "Gary Zielinski",
          "slug": "gary-zielinski"
        },
        {
          "name": "Bennett Salvatore",
          "slug": "bennett-salvatore"
        },
        {
          "name": "Jason Phillips",
          "slug": "jason-phillips"
        }
      ]
    },
    {
      "pts": 22,
      "reb": 2,
      "ast": 2,
      "team_abbr": "MIA",
      "opp_abbr": "WAS",
      "game_date": "2007-12-13",
      "game_id": "0020700325",
      "crew": [
        {
          "name": "Marc Davis",
          "slug": "marc-davis"
        },
        {
          "name": "Kevin Fehr",
          "slug": "kevin-fehr"
        },
        {
          "name": "Steve Javie",
          "slug": "steve-javie"
        }
      ]
    },
    {
      "pts": 20,
      "reb": 1,
      "ast": 2,
      "team_abbr": "MIA",
      "opp_abbr": "GSW",
      "game_date": "2008-03-07",
      "game_id": "0020700916",
      "crew": [
        {
          "name": "Michael Smith",
          "slug": "michael-smith"
        },
        {
          "name": "Eddie Rush",
          "slug": "eddie-rush"
        },
        {
          "name": "Phil Robinson",
          "slug": "phil-robinson"
        }
      ]
    },
    {
      "pts": 18,
      "reb": 7,
      "ast": 9,
      "team_abbr": "MIA",
      "opp_abbr": "NOH",
      "game_date": "2008-04-02",
      "game_id": "0020701117",
      "crew": [
        {
          "name": "Tommy Nunez Jr.",
          "slug": "tommy-nunez"
        },
        {
          "name": "Scott Foster",
          "slug": "scott-foster"
        },
        {
          "name": "Rodney Mott",
          "slug": "rodney-mott"
        }
      ]
    },
    {
      "pts": 17,
      "reb": 0,
      "ast": 0,
      "team_abbr": "MIA",
      "opp_abbr": "MEM",
      "game_date": "2008-01-06",
      "game_id": "0020700494",
      "crew": []
    },
    {
      "pts": 17,
      "reb": 1,
      "ast": 4,
      "team_abbr": "MIA",
      "opp_abbr": "MIL",
      "game_date": "2008-03-18",
      "game_id": "0020701000",
      "crew": [
        {
          "name": "Jimmy Clark",
          "slug": "jimmy-clark"
        },
        {
          "name": "Tommy Nunez Jr.",
          "slug": "tommy-nunez"
        },
        {
          "name": "Rodney Mott",
          "slug": "rodney-mott"
        }
      ]
    },
    {
      "pts": 16,
      "reb": 3,
      "ast": 6,
      "team_abbr": "MIA",
      "opp_abbr": "CHI",
      "game_date": "2008-04-08",
      "game_id": "0020701155",
      "crew": [
        {
          "name": "Mark Wunderlich",
          "slug": "mark-wunderlich"
        },
        {
          "name": "Steve Javie",
          "slug": "steve-javie"
        },
        {
          "name": "Pat Fraher",
          "slug": "pat-fraher"
        }
      ]
    },
    {
      "pts": 15,
      "reb": 4,
      "ast": 6,
      "team_abbr": "MIA",
      "opp_abbr": "IND",
      "game_date": "2008-03-31",
      "game_id": "0020701100",
      "crew": [
        {
          "name": "Pat Fraher",
          "slug": "pat-fraher"
        },
        {
          "name": "Mike Callahan",
          "slug": "mike-callahan"
        },
        {
          "name": "Tony Brothers",
          "slug": "tony-brothers"
        }
      ]
    }
  ]
}