{
  "summary": {
    "name": "Cody Martin",
    "slug": "cody-martin",
    "first_season": "2019-20",
    "last_season": "2025-26",
    "teams": [
      "CHA",
      "IND",
      "PHX"
    ],
    "games_total": 263,
    "eras": [
      "espn",
      "nba"
    ]
  },
  "ref_splits": [
    {
      "ref_name": "Nate Green",
      "ref_slug": "nate-green",
      "player_id": "3138161",
      "n_games": 15,
      "pts_with_ref": 6.27,
      "pts_baseline": 5.83,
      "pts_swing": 0.44,
      "reb_with_ref": 3.33,
      "reb_baseline": 3.71,
      "reb_swing": -0.38,
      "ast_with_ref": 1.87,
      "ast_baseline": 2.29,
      "ast_swing": -0.43,
      "seasons": [
        "2019-20",
        "2020-21",
        "2021-22",
        "2023-24",
        "2024-25",
        "2025-26"
      ]
    },
    {
      "ref_name": "Tyler Ford",
      "ref_slug": "tyler-ford",
      "player_id": "1628998",
      "n_games": 15,
      "pts_with_ref": 8.07,
      "pts_baseline": 6.67,
      "pts_swing": 1.39,
      "reb_with_ref": 3.2,
      "reb_baseline": 3.91,
      "reb_swing": -0.71,
      "ast_with_ref": 1.8,
      "ast_baseline": 2.32,
      "ast_swing": -0.52,
      "seasons": [
        "2020-21",
        "2021-22",
        "2022-23",
        "2023-24",
        "2024-25"
      ]
    },
    {
      "ref_name": "Zach Zarba",
      "ref_slug": "zach-zarba",
      "player_id": "1628998",
      "n_games": 15,
      "pts_with_ref": 6.6,
      "pts_baseline": 6.01,
      "pts_swing": 0.59,
      "reb_with_ref": 3.6,
      "reb_baseline": 3.76,
      "reb_swing": -0.16,
      "ast_with_ref": 2.6,
      "ast_baseline": 2.1,
      "ast_swing": 0.5,
      "seasons": [
        "2019-20",
        "2020-21",
        "2021-22",
        "2023-24",
        "2024-25"
      ]
    }
  ],
  "top_games": [
    {
      "pts": 25,
      "reb": 4,
      "ast": 2,
      "team_abbr": "CHA",
      "opp_abbr": "TOR",
      "game_date": "2024-10-30",
      "game_id": "401704683",
      "crew": [
        {
          "name": "Nick Buchert",
          "slug": "nick-buchert"
        },
        {
          "name": "Tyler Ford",
          "slug": "tyler-ford"
        },
        {
          "name": "Pat O'Connell",
          "slug": "pat-oconnell"
        }
      ]
    },
    {
      "pts": 21,
      "reb": 8,
      "ast": 3,
      "team_abbr": "CHA",
      "opp_abbr": "SAS",
      "game_date": "2021-12-15",
      "game_id": "0022100423",
      "crew": [
        {
          "name": "Tony Brothers",
          "slug": "tony-brothers"
        },
        {
          "name": "Gediminas Petraitis",
          "slug": "gediminas-petraitis"
        },
        {
          "name": "John Conley",
          "slug": "john-conley"
        }
      ]
    },
    {
      "pts": 19,
      "reb": 5,
      "ast": 8,
      "team_abbr": "CHA",
      "opp_abbr": "TOR",
      "game_date": "2024-02-08",
      "game_id": "401585354",
      "crew": [
        {
          "name": "Scott Foster",
          "slug": "scott-foster"
        },
        {
          "name": "Karl Lane",
          "slug": "karl-lane"
        },
        {
          "name": "Nate Green",
          "slug": "nate-green"
        }
      ]
    },
    {
      "pts": 19,
      "reb": 6,
      "ast": 4,
      "team_abbr": "CHA",
      "opp_abbr": "ATL",
      "game_date": "2021-12-05",
      "game_id": "0022100350",
      "crew": [
        {
          "name": "Zach Zarba",
          "slug": "zach-zarba"
        },
        {
          "name": "Brian Forte",
          "slug": "brian-forte"
        },
        {
          "name": "Aaron Smith",
          "slug": "aaron-smith"
        }
      ]
    },
    {
      "pts": 19,
      "reb": 8,
      "ast": 5,
      "team_abbr": "CHA",
      "opp_abbr": "SAC",
      "game_date": "2021-12-10",
      "game_id": "0022100382",
      "crew": [
        {
          "name": "Sean Wright",
          "slug": "sean-wright"
        },
        {
          "name": "Dedric Taylor",
          "slug": "dedric-taylor"
        },
        {
          "name": "John Butler",
          "slug": "john-butler"
        }
      ]
    },
    {
      "pts": 15,
      "reb": 5,
      "ast": 4,
      "team_abbr": "CHA",
      "opp_abbr": "NOP",
      "game_date": "2022-03-11",
      "game_id": "0022101001",
      "crew": [
        {
          "name": "Ben Taylor",
          "slug": "ben-taylor"
        },
        {
          "name": "Matt Myers",
          "slug": "matt-myers"
        },
        {
          "name": "Mitchell Ervin",
          "slug": "mitchell-ervin"
        }
      ]
    },
    {
      "pts": 15,
      "reb": 3,
      "ast": 1,
      "team_abbr": "CHA",
      "opp_abbr": "DET",
      "game_date": "2024-11-22",
      "game_id": "401704826",
      "crew": [
        {
          "name": "John Goble",
          "slug": "john-goble"
        },
        {
          "name": "Marat Kogut",
          "slug": "marat-kogut"
        },
        {
          "name": "Danielle Scott",
          "slug": "danielle-scott"
        }
      ]
    },
    {
      "pts": 15,
      "reb": 5,
      "ast": 4,
      "team_abbr": "CHA",
      "opp_abbr": "IND",
      "game_date": "2024-11-09",
      "game_id": "401704750",
      "crew": [
        {
          "name": "Josh Tiven",
          "slug": "josh-tiven"
        },
        {
          "name": "Andy Nagy",
          "slug": "andy-nagy"
        },
        {
          "name": "Intae Hwang",
          "slug": "intae-hwang"
        }
      ]
    },
    {
      "pts": 15,
      "reb": 3,
      "ast": 2,
      "team_abbr": "CHA",
      "opp_abbr": "MIA",
      "game_date": "2021-10-29",
      "game_id": "0022100073",
      "crew": [
        {
          "name": "Tony Brothers",
          "slug": "tony-brothers"
        },
        {
          "name": "Brian Forte",
          "slug": "brian-forte"
        },
        {
          "name": "Aaron Smith",
          "slug": "aaron-smith"
        }
      ]
    },
    {
      "pts": 14,
      "reb": 6,
      "ast": 4,
      "team_abbr": "CHA",
      "opp_abbr": "PHI",
      "game_date": "2021-12-06",
      "game_id": "0022100353",
      "crew": [
        {
          "name": "Josh Tiven",
          "slug": "josh-tiven"
        },
        {
          "name": "Brandon Adair",
          "slug": "brandon-adair"
        },
        {
          "name": "Jacyn Goble",
          "slug": "jacyn-goble"
        }
      ]
    }
  ]
}