{
  "summary": {
    "name": "Damyean Dotson",
    "slug": "damyean-dotson",
    "first_season": "2017-18",
    "last_season": "2021-22",
    "teams": [
      "CLE",
      "NYK"
    ],
    "games_total": 213,
    "eras": [
      "nba"
    ]
  },
  "ref_splits": [
    {
      "ref_name": "Scott Twardoski",
      "ref_slug": "scott-twardoski",
      "player_id": "1628422",
      "n_games": 17,
      "pts_with_ref": 5.53,
      "pts_baseline": 7.95,
      "pts_swing": -2.42,
      "reb_with_ref": 2.0,
      "reb_baseline": 2.55,
      "reb_swing": -0.55,
      "ast_with_ref": 1.71,
      "ast_baseline": 1.72,
      "ast_swing": -0.01,
      "seasons": [
        "2017-18",
        "2018-19",
        "2019-20",
        "2020-21"
      ]
    }
  ],
  "top_games": [
    {
      "pts": 30,
      "reb": 11,
      "ast": 1,
      "team_abbr": "NYK",
      "opp_abbr": "MIA",
      "game_date": "2018-04-06",
      "game_id": "0021701186",
      "crew": [
        {
          "name": "Ben Taylor",
          "slug": "ben-taylor"
        },
        {
          "name": "Derek Richardson",
          "slug": "derek-richardson"
        },
        {
          "name": "Sean Wright",
          "slug": "sean-wright"
        }
      ]
    },
    {
      "pts": 27,
      "reb": 5,
      "ast": 2,
      "team_abbr": "NYK",
      "opp_abbr": "SAS",
      "game_date": "2019-02-24",
      "game_id": "0021800896",
      "crew": [
        {
          "name": "Tony Brothers",
          "slug": "tony-brothers"
        },
        {
          "name": "Mousa Dagher",
          "slug": "mousa-dagher"
        },
        {
          "name": "Pat Fraher",
          "slug": "pat-fraher"
        }
      ]
    },
    {
      "pts": 26,
      "reb": 6,
      "ast": 6,
      "team_abbr": "NYK",
      "opp_abbr": "MIN",
      "game_date": "2019-03-10",
      "game_id": "0021800998",
      "crew": [
        {
          "name": "Marc Davis",
          "slug": "marc-davis"
        },
        {
          "name": "Justin Van Duyne",
          "slug": "justin-van-duyne"
        },
        {
          "name": "Tyler Ford",
          "slug": "tyler-ford"
        }
      ]
    },
    {
      "pts": 25,
      "reb": 6,
      "ast": 1,
      "team_abbr": "NYK",
      "opp_abbr": "LAL",
      "game_date": "2019-03-17",
      "game_id": "0021801042",
      "crew": [
        {
          "name": "Scott Wall",
          "slug": "scott-wall"
        },
        {
          "name": "Ashley Moyer-Gleich",
          "slug": "ashley-moyer-gleich"
        },
        {
          "name": "Pat Fraher",
          "slug": "pat-fraher"
        }
      ]
    },
    {
      "pts": 22,
      "reb": 6,
      "ast": 0,
      "team_abbr": "NYK",
      "opp_abbr": "BOS",
      "game_date": "2019-02-01",
      "game_id": "0021800771",
      "crew": [
        {
          "name": "Marc Davis",
          "slug": "marc-davis"
        },
        {
          "name": "Nick Buchert",
          "slug": "nick-buchert"
        },
        {
          "name": "Michael Smith",
          "slug": "michael-smith"
        }
      ]
    },
    {
      "pts": 21,
      "reb": 1,
      "ast": 0,
      "team_abbr": "NYK",
      "opp_abbr": "TOR",
      "game_date": "2020-01-24",
      "game_id": "0021900672",
      "crew": [
        {
          "name": "John Butler",
          "slug": "john-butler"
        },
        {
          "name": "J.T. Orr",
          "slug": "j-t-orr"
        },
        {
          "name": "Tony Brothers",
          "slug": "tony-brothers"
        }
      ]
    },
    {
      "pts": 21,
      "reb": 2,
      "ast": 8,
      "team_abbr": "CLE",
      "opp_abbr": "MIL",
      "game_date": "2021-01-09",
      "game_id": "0022000137",
      "crew": [
        {
          "name": "Bill Kennedy",
          "slug": "bill-kennedy"
        },
        {
          "name": "Dedric Taylor",
          "slug": "dedric-taylor"
        },
        {
          "name": "Derek Richardson",
          "slug": "derek-richardson"
        }
      ]
    },
    {
      "pts": 21,
      "reb": 2,
      "ast": 2,
      "team_abbr": "NYK",
      "opp_abbr": "SAS",
      "game_date": "2019-03-15",
      "game_id": "0021801032",
      "crew": [
        {
          "name": "Matt Boland",
          "slug": "matt-boland"
        },
        {
          "name": "Tom Washington",
          "slug": "tom-washington"
        },
        {
          "name": "Kevin Scott",
          "slug": "kevin-scott"
        }
      ]
    },
    {
      "pts": 21,
      "reb": 1,
      "ast": 3,
      "team_abbr": "NYK",
      "opp_abbr": "UTA",
      "game_date": "2019-03-20",
      "game_id": "0021801068",
      "crew": [
        {
          "name": "Ed Malloy",
          "slug": "ed-malloy"
        },
        {
          "name": "Matt Myers",
          "slug": "matt-myers"
        },
        {
          "name": "Scott Twardoski",
          "slug": "scott-twardoski"
        }
      ]
    },
    {
      "pts": 21,
      "reb": 5,
      "ast": 1,
      "team_abbr": "NYK",
      "opp_abbr": "MIL",
      "game_date": "2018-12-01",
      "game_id": "0021800330",
      "crew": [
        {
          "name": "Jason Phillips",
          "slug": "jason-phillips"
        },
        {
          "name": "JB DeRosa",
          "slug": "jb-derosa"
        },
        {
          "name": "Matt Boland",
          "slug": "matt-boland"
        }
      ]
    }
  ]
}