{
  "summary": {
    "name": "Jalen Johnson",
    "slug": "jalen-johnson",
    "first_season": "2021-22",
    "last_season": "2025-26",
    "teams": [
      "ATL"
    ],
    "games_total": 270,
    "eras": [
      "espn",
      "nba"
    ]
  },
  "ref_splits": [
    {
      "ref_name": "Gediminas Petraitis",
      "ref_slug": "gediminas-petraitis",
      "player_id": "4701230",
      "n_games": 17,
      "pts_with_ref": 15.82,
      "pts_baseline": 16.28,
      "pts_swing": -0.46,
      "reb_with_ref": 9.0,
      "reb_baseline": 7.97,
      "reb_swing": 1.03,
      "ast_with_ref": 5.0,
      "ast_baseline": 4.85,
      "ast_swing": 0.15,
      "seasons": [
        "2021-22",
        "2022-23",
        "2023-24",
        "2024-25",
        "2025-26"
      ]
    },
    {
      "ref_name": "Ray Acosta",
      "ref_slug": "ray-acosta",
      "player_id": "4701230",
      "n_games": 17,
      "pts_with_ref": 18.0,
      "pts_baseline": 16.97,
      "pts_swing": 1.03,
      "reb_with_ref": 7.59,
      "reb_baseline": 8.58,
      "reb_swing": -0.99,
      "ast_with_ref": 5.06,
      "ast_baseline": 4.86,
      "ast_swing": 0.2,
      "seasons": [
        "2022-23",
        "2023-24",
        "2024-25",
        "2025-26"
      ]
    },
    {
      "ref_name": "Tyler Ford",
      "ref_slug": "tyler-ford",
      "player_id": "4701230",
      "n_games": 17,
      "pts_with_ref": 16.12,
      "pts_baseline": 14.73,
      "pts_swing": 1.39,
      "reb_with_ref": 8.06,
      "reb_baseline": 7.67,
      "reb_swing": 0.39,
      "ast_with_ref": 3.76,
      "ast_baseline": 4.1,
      "ast_swing": -0.33,
      "seasons": [
        "2021-22",
        "2022-23",
        "2023-24",
        "2024-25",
        "2025-26"
      ]
    },
    {
      "ref_name": "Ed Malloy",
      "ref_slug": "ed-malloy",
      "player_id": "4701230",
      "n_games": 16,
      "pts_with_ref": 10.38,
      "pts_baseline": 12.0,
      "pts_swing": -1.63,
      "reb_with_ref": 6.44,
      "reb_baseline": 6.38,
      "reb_swing": 0.05,
      "ast_with_ref": 2.44,
      "ast_baseline": 3.09,
      "ast_swing": -0.65,
      "seasons": [
        "2021-22",
        "2022-23",
        "2023-24",
        "2024-25",
        "2025-26"
      ]
    },
    {
      "ref_name": "Scott Foster",
      "ref_slug": "scott-foster",
      "player_id": "4701230",
      "n_games": 16,
      "pts_with_ref": 12.69,
      "pts_baseline": 14.24,
      "pts_swing": -1.56,
      "reb_with_ref": 6.62,
      "reb_baseline": 7.34,
      "reb_swing": -0.72,
      "ast_with_ref": 4.38,
      "ast_baseline": 4.05,
      "ast_swing": 0.32,
      "seasons": [
        "2022-23",
        "2023-24",
        "2024-25",
        "2025-26"
      ]
    },
    {
      "ref_name": "Karl Lane",
      "ref_slug": "karl-lane",
      "player_id": "4701230",
      "n_games": 15,
      "pts_with_ref": 13.33,
      "pts_baseline": 15.31,
      "pts_swing": -1.98,
      "reb_with_ref": 6.87,
      "reb_baseline": 7.79,
      "reb_swing": -0.93,
      "ast_with_ref": 3.73,
      "ast_baseline": 4.31,
      "ast_swing": -0.58,
      "seasons": [
        "2022-23",
        "2023-24",
        "2024-25",
        "2025-26"
      ]
    },
    {
      "ref_name": "Pat Fraher",
      "ref_slug": "pat-fraher",
      "player_id": "4701230",
      "n_games": 15,
      "pts_with_ref": 11.4,
      "pts_baseline": 11.92,
      "pts_swing": -0.52,
      "reb_with_ref": 5.87,
      "reb_baseline": 6.53,
      "reb_swing": -0.66,
      "ast_with_ref": 3.0,
      "ast_baseline": 3.08,
      "ast_swing": -0.08,
      "seasons": [
        "2021-22",
        "2022-23",
        "2023-24",
        "2024-25",
        "2025-26"
      ]
    }
  ],
  "top_games": [
    {
      "pts": 43,
      "reb": 11,
      "ast": 9,
      "team_abbr": "ATL",
      "opp_abbr": "CHA",
      "game_date": "2025-12-19",
      "game_id": "401810226",
      "crew": [
        {
          "name": "Tony Brothers",
          "slug": "tony-brothers"
        },
        {
          "name": "Karl Lane",
          "slug": "karl-lane"
        },
        {
          "name": "Brandon Schwab",
          "slug": "brandon-schwab"
        }
      ]
    },
    {
      "pts": 41,
      "reb": 14,
      "ast": 7,
      "team_abbr": "ATL",
      "opp_abbr": "PHI",
      "game_date": "2025-11-30",
      "game_id": "401810159",
      "crew": [
        {
          "name": "James Capers",
          "slug": "james-capers"
        },
        {
          "name": "Derrick Collins",
          "slug": "derrick-collins"
        },
        {
          "name": "Brent Barnaky",
          "slug": "brent-barnaky"
        }
      ]
    },
    {
      "pts": 36,
      "reb": 11,
      "ast": 9,
      "team_abbr": "ATL",
      "opp_abbr": "CHI",
      "game_date": "2025-12-21",
      "game_id": "401810251",
      "crew": [
        {
          "name": "Marat Kogut",
          "slug": "marat-kogut"
        },
        {
          "name": "Mitchell Ervin",
          "slug": "mitchell-ervin"
        },
        {
          "name": "Jonathan Sterling",
          "slug": "jonathan-sterling"
        }
      ]
    },
    {
      "pts": 35,
      "reb": 10,
      "ast": 7,
      "team_abbr": "ATL",
      "opp_abbr": "PHI",
      "game_date": "2026-03-07",
      "game_id": "401810772",
      "crew": [
        {
          "name": "John Goble",
          "slug": "john-goble"
        },
        {
          "name": "Ray Acosta",
          "slug": "ray-acosta"
        },
        {
          "name": "Suyash Mehta",
          "slug": "suyash-mehta"
        }
      ]
    },
    {
      "pts": 34,
      "reb": 10,
      "ast": 6,
      "team_abbr": "ATL",
      "opp_abbr": "MIN",
      "game_date": "2025-12-31",
      "game_id": "401810318",
      "crew": [
        {
          "name": "Sean Corbin",
          "slug": "sean-corbin"
        },
        {
          "name": "Ray Acosta",
          "slug": "ray-acosta"
        },
        {
          "name": "Matt Kallio",
          "slug": "matt-kallio"
        }
      ]
    },
    {
      "pts": 33,
      "reb": 11,
      "ast": 10,
      "team_abbr": "ATL",
      "opp_abbr": "IND",
      "game_date": "2026-02-01",
      "game_id": "401810553",
      "crew": [
        {
          "name": "Che Flores",
          "slug": "che-flores"
        },
        {
          "name": "Nick Buchert",
          "slug": "nick-buchert"
        },
        {
          "name": "JB DeRosa",
          "slug": "jb-derosa"
        }
      ]
    },
    {
      "pts": 32,
      "reb": 10,
      "ast": 5,
      "team_abbr": "ATL",
      "opp_abbr": "PHI",
      "game_date": "2026-02-20",
      "game_id": "401810649",
      "crew": [
        {
          "name": "Nick Buchert",
          "slug": "nick-buchert"
        },
        {
          "name": "Tyler Ford",
          "slug": "tyler-ford"
        },
        {
          "name": "JD Ralls",
          "slug": "jd-ralls"
        }
      ]
    },
    {
      "pts": 32,
      "reb": 15,
      "ast": 8,
      "team_abbr": "ATL",
      "opp_abbr": "MEM",
      "game_date": "2026-01-22",
      "game_id": "401810478",
      "crew": [
        {
          "name": "Mitchell Ervin",
          "slug": "mitchell-ervin"
        },
        {
          "name": "Nate Green",
          "slug": "nate-green"
        },
        {
          "name": "Matt Kallio",
          "slug": "matt-kallio"
        }
      ]
    },
    {
      "pts": 31,
      "reb": 18,
      "ast": 14,
      "team_abbr": "ATL",
      "opp_abbr": "UTA",
      "game_date": "2025-11-14",
      "game_id": "401810082",
      "crew": [
        {
          "name": "Dedric Taylor",
          "slug": "dedric-taylor"
        },
        {
          "name": "Leon Wood",
          "slug": "leon-wood"
        },
        {
          "name": "Tyler Ford",
          "slug": "tyler-ford"
        }
      ]
    },
    {
      "pts": 31,
      "reb": 9,
      "ast": 8,
      "team_abbr": "ATL",
      "opp_abbr": "CHA",
      "game_date": "2026-02-08",
      "game_id": "401810606",
      "crew": [
        {
          "name": "Jacyn Goble",
          "slug": "jacyn-goble"
        },
        {
          "name": "Ashley Moyer-Gleich",
          "slug": "ashley-moyer-gleich"
        },
        {
          "name": "Biniam Maru",
          "slug": "biniam-maru"
        }
      ]
    }
  ]
}