{
  "summary": {
    "name": "Jamario Moon",
    "slug": "jamario-moon",
    "first_season": "2007-08",
    "last_season": "2011-12",
    "teams": [
      "CHA",
      "CLE",
      "LAC",
      "MIA",
      "TOR"
    ],
    "games_total": 305,
    "eras": [
      "nba"
    ]
  },
  "ref_splits": [
    {
      "ref_name": "Tony Brothers",
      "ref_slug": "tony-brothers",
      "player_id": "200081",
      "n_games": 21,
      "pts_with_ref": 7.52,
      "pts_baseline": 5.85,
      "pts_swing": 1.67,
      "reb_with_ref": 3.57,
      "reb_baseline": 3.96,
      "reb_swing": -0.39,
      "ast_with_ref": 1.14,
      "ast_baseline": 0.97,
      "ast_swing": 0.17,
      "seasons": [
        "2007-08",
        "2008-09",
        "2009-10",
        "2010-11",
        "2011-12"
      ]
    },
    {
      "ref_name": "David Guthrie",
      "ref_slug": "david-guthrie",
      "player_id": "200081",
      "n_games": 19,
      "pts_with_ref": 6.42,
      "pts_baseline": 6.24,
      "pts_swing": 0.18,
      "reb_with_ref": 4.63,
      "reb_baseline": 4.31,
      "reb_swing": 0.32,
      "ast_with_ref": 1.16,
      "ast_baseline": 1.0,
      "ast_swing": 0.16,
      "seasons": [
        "2007-08",
        "2008-09",
        "2009-10",
        "2010-11",
        "2011-12"
      ]
    },
    {
      "ref_name": "Ken Mauer",
      "ref_slug": "ken-mauer",
      "player_id": "200081",
      "n_games": 19,
      "pts_with_ref": 6.37,
      "pts_baseline": 5.98,
      "pts_swing": 0.39,
      "reb_with_ref": 4.53,
      "reb_baseline": 3.91,
      "reb_swing": 0.62,
      "ast_with_ref": 0.79,
      "ast_baseline": 0.96,
      "ast_swing": -0.17,
      "seasons": [
        "2007-08",
        "2008-09",
        "2009-10",
        "2010-11"
      ]
    },
    {
      "ref_name": "Tom Washington",
      "ref_slug": "tom-washington",
      "player_id": "200081",
      "n_games": 18,
      "pts_with_ref": 4.89,
      "pts_baseline": 5.95,
      "pts_swing": -1.06,
      "reb_with_ref": 4.11,
      "reb_baseline": 4.13,
      "reb_swing": -0.02,
      "ast_with_ref": 1.06,
      "ast_baseline": 0.97,
      "ast_swing": 0.08,
      "seasons": [
        "2007-08",
        "2008-09",
        "2009-10",
        "2010-11",
        "2011-12"
      ]
    },
    {
      "ref_name": "Tony Brown",
      "ref_slug": "tony-brown",
      "player_id": "200081",
      "n_games": 18,
      "pts_with_ref": 6.89,
      "pts_baseline": 5.99,
      "pts_swing": 0.9,
      "reb_with_ref": 4.89,
      "reb_baseline": 4.13,
      "reb_swing": 0.76,
      "ast_with_ref": 0.56,
      "ast_baseline": 0.97,
      "ast_swing": -0.42,
      "seasons": [
        "2007-08",
        "2008-09",
        "2009-10",
        "2010-11",
        "2011-12"
      ]
    },
    {
      "ref_name": "Zach Zarba",
      "ref_slug": "zach-zarba",
      "player_id": "200081",
      "n_games": 18,
      "pts_with_ref": 6.06,
      "pts_baseline": 5.95,
      "pts_swing": 0.11,
      "reb_with_ref": 4.28,
      "reb_baseline": 3.94,
      "reb_swing": 0.33,
      "ast_with_ref": 0.67,
      "ast_baseline": 0.95,
      "ast_swing": -0.28,
      "seasons": [
        "2007-08",
        "2008-09",
        "2009-10",
        "2010-11"
      ]
    },
    {
      "ref_name": "Bill Kennedy",
      "ref_slug": "bill-kennedy",
      "player_id": "200081",
      "n_games": 17,
      "pts_with_ref": 5.29,
      "pts_baseline": 6.23,
      "pts_swing": -0.94,
      "reb_with_ref": 4.24,
      "reb_baseline": 4.18,
      "reb_swing": 0.06,
      "ast_with_ref": 1.06,
      "ast_baseline": 1.0,
      "ast_swing": 0.06,
      "seasons": [
        "2007-08",
        "2008-09",
        "2009-10",
        "2010-11"
      ]
    },
    {
      "ref_name": "Derek Richardson",
      "ref_slug": "derek-richardson",
      "player_id": "200081",
      "n_games": 17,
      "pts_with_ref": 6.12,
      "pts_baseline": 5.88,
      "pts_swing": 0.24,
      "reb_with_ref": 3.24,
      "reb_baseline": 3.97,
      "reb_swing": -0.74,
      "ast_with_ref": 1.0,
      "ast_baseline": 0.99,
      "ast_swing": 0.01,
      "seasons": [
        "2007-08",
        "2008-09",
        "2009-10",
        "2010-11",
        "2011-12"
      ]
    },
    {
      "ref_name": "Joe Crawford",
      "ref_slug": "joe-crawford",
      "player_id": "200081",
      "n_games": 17,
      "pts_with_ref": 7.18,
      "pts_baseline": 5.93,
      "pts_swing": 1.25,
      "reb_with_ref": 4.41,
      "reb_baseline": 3.84,
      "reb_swing": 0.57,
      "ast_with_ref": 1.12,
      "ast_baseline": 0.95,
      "ast_swing": 0.17,
      "seasons": [
        "2007-08",
        "2008-09",
        "2009-10",
        "2010-11"
      ]
    },
    {
      "ref_name": "Bennett Salvatore",
      "ref_slug": "bennett-salvatore",
      "player_id": "200081",
      "n_games": 16,
      "pts_with_ref": 5.06,
      "pts_baseline": 5.88,
      "pts_swing": -0.82,
      "reb_with_ref": 4.31,
      "reb_baseline": 3.95,
      "reb_swing": 0.36,
      "ast_with_ref": 1.0,
      "ast_baseline": 0.9,
      "ast_swing": 0.1,
      "seasons": [
        "2007-08",
        "2008-09",
        "2009-10",
        "2010-11"
      ]
    },
    {
      "ref_name": "Greg Willard",
      "ref_slug": "greg-willard",
      "player_id": "200081",
      "n_games": 16,
      "pts_with_ref": 5.81,
      "pts_baseline": 5.7,
      "pts_swing": 0.11,
      "reb_with_ref": 3.31,
      "reb_baseline": 3.97,
      "reb_swing": -0.66,
      "ast_with_ref": 0.38,
      "ast_baseline": 0.93,
      "ast_swing": -0.55,
      "seasons": [
        "2007-08",
        "2008-09",
        "2009-10",
        "2010-11",
        "2011-12"
      ]
    },
    {
      "ref_name": "Joe Forte",
      "ref_slug": "joe-forte",
      "player_id": "200081",
      "n_games": 16,
      "pts_with_ref": 8.56,
      "pts_baseline": 7.36,
      "pts_swing": 1.21,
      "reb_with_ref": 5.12,
      "reb_baseline": 5.12,
      "reb_swing": 0.01,
      "ast_with_ref": 1.25,
      "ast_baseline": 1.1,
      "ast_swing": 0.15,
      "seasons": [
        "2007-08",
        "2008-09",
        "2009-10"
      ]
    },
    {
      "ref_name": "Marc Davis",
      "ref_slug": "marc-davis",
      "player_id": "200081",
      "n_games": 16,
      "pts_with_ref": 5.44,
      "pts_baseline": 5.49,
      "pts_swing": -0.06,
      "reb_with_ref": 4.06,
      "reb_baseline": 3.71,
      "reb_swing": 0.35,
      "ast_with_ref": 1.12,
      "ast_baseline": 0.89,
      "ast_swing": 0.23,
      "seasons": [
        "2007-08",
        "2008-09",
        "2009-10",
        "2010-11"
      ]
    },
    {
      "ref_name": "Sean Wright",
      "ref_slug": "sean-wright",
      "player_id": "200081",
      "n_games": 16,
      "pts_with_ref": 7.38,
      "pts_baseline": 5.85,
      "pts_swing": 1.52,
      "reb_with_ref": 3.56,
      "reb_baseline": 3.95,
      "reb_swing": -0.39,
      "ast_with_ref": 1.0,
      "ast_baseline": 0.97,
      "ast_swing": 0.03,
      "seasons": [
        "2007-08",
        "2008-09",
        "2009-10",
        "2010-11"
      ]
    },
    {
      "ref_name": "Bill Spooner",
      "ref_slug": "bill-spooner",
      "player_id": "200081",
      "n_games": 15,
      "pts_with_ref": 5.0,
      "pts_baseline": 6.49,
      "pts_swing": -1.49,
      "reb_with_ref": 4.13,
      "reb_baseline": 4.36,
      "reb_swing": -0.23,
      "ast_with_ref": 1.2,
      "ast_baseline": 1.01,
      "ast_swing": 0.19,
      "seasons": [
        "2007-08",
        "2008-09",
        "2009-10",
        "2010-11"
      ]
    },
    {
      "ref_name": "Derrick Collins",
      "ref_slug": "derrick-collins",
      "player_id": "200081",
      "n_games": 15,
      "pts_with_ref": 6.93,
      "pts_baseline": 6.17,
      "pts_swing": 0.77,
      "reb_with_ref": 3.93,
      "reb_baseline": 4.39,
      "reb_swing": -0.45,
      "ast_with_ref": 0.47,
      "ast_baseline": 0.97,
      "ast_swing": -0.5,
      "seasons": [
        "2007-08",
        "2008-09",
        "2009-10",
        "2010-11",
        "2011-12"
      ]
    },
    {
      "ref_name": "Eddie Rush",
      "ref_slug": "eddie-rush",
      "player_id": "200081",
      "n_games": 15,
      "pts_with_ref": 6.53,
      "pts_baseline": 6.08,
      "pts_swing": 0.45,
      "reb_with_ref": 3.2,
      "reb_baseline": 3.89,
      "reb_swing": -0.69,
      "ast_with_ref": 0.67,
      "ast_baseline": 0.93,
      "ast_swing": -0.27,
      "seasons": [
        "2007-08",
        "2008-09",
        "2009-10"
      ]
    },
    {
      "ref_name": "Kevin Fehr",
      "ref_slug": "kevin-fehr",
      "player_id": "200081",
      "n_games": 15,
      "pts_with_ref": 5.93,
      "pts_baseline": 6.08,
      "pts_swing": -0.15,
      "reb_with_ref": 3.4,
      "reb_baseline": 4.13,
      "reb_swing": -0.73,
      "ast_with_ref": 0.47,
      "ast_baseline": 1.01,
      "ast_swing": -0.54,
      "seasons": [
        "2007-08",
        "2008-09",
        "2009-10",
        "2010-11",
        "2011-12"
      ]
    },
    {
      "ref_name": "Mike Callahan",
      "ref_slug": "mike-callahan",
      "player_id": "200081",
      "n_games": 15,
      "pts_with_ref": 4.07,
      "pts_baseline": 5.55,
      "pts_swing": -1.48,
      "reb_with_ref": 2.8,
      "reb_baseline": 3.69,
      "reb_swing": -0.89,
      "ast_with_ref": 0.67,
      "ast_baseline": 0.91,
      "ast_swing": -0.25,
      "seasons": [
        "2007-08",
        "2008-09",
        "2009-10",
        "2010-11",
        "2011-12"
      ]
    },
    {
      "ref_name": "Olandis Poole",
      "ref_slug": "olandis-poole",
      "player_id": "200081",
      "n_games": 15,
      "pts_with_ref": 5.8,
      "pts_baseline": 6.22,
      "pts_swing": -0.42,
      "reb_with_ref": 5.0,
      "reb_baseline": 4.13,
      "reb_swing": 0.87,
      "ast_with_ref": 0.93,
      "ast_baseline": 1.02,
      "ast_swing": -0.09,
      "seasons": [
        "2007-08",
        "2008-09",
        "2009-10",
        "2010-11"
      ]
    },
    {
      "ref_name": "Sean Corbin",
      "ref_slug": "sean-corbin",
      "player_id": "200081",
      "n_games": 15,
      "pts_with_ref": 6.53,
      "pts_baseline": 6.52,
      "pts_swing": 0.01,
      "reb_with_ref": 3.67,
      "reb_baseline": 4.32,
      "reb_swing": -0.65,
      "ast_with_ref": 1.0,
      "ast_baseline": 1.03,
      "ast_swing": -0.03,
      "seasons": [
        "2007-08",
        "2008-09",
        "2009-10"
      ]
    }
  ],
  "top_games": [
    {
      "pts": 17,
      "reb": 12,
      "ast": 4,
      "team_abbr": "TOR",
      "opp_abbr": "ORL",
      "game_date": "2008-02-20",
      "game_id": "0020700790",
      "crew": []
    },
    {
      "pts": 17,
      "reb": 9,
      "ast": 1,
      "team_abbr": "TOR",
      "opp_abbr": "PHI",
      "game_date": "2008-01-19",
      "game_id": "0020700583",
      "crew": [
        {
          "name": "Sean Wright",
          "slug": "sean-wright"
        },
        {
          "name": "Monty McCutchen",
          "slug": "monty-mccutchen"
        },
        {
          "name": "Joe Crawford",
          "slug": "joe-crawford"
        }
      ]
    },
    {
      "pts": 17,
      "reb": 12,
      "ast": 0,
      "team_abbr": "MIA",
      "opp_abbr": "NYK",
      "game_date": "2009-02-28",
      "game_id": "0020800877",
      "crew": [
        {
          "name": "David Guthrie",
          "slug": "david-guthrie"
        },
        {
          "name": "Mark Ayotte",
          "slug": "mark-ayotte"
        },
        {
          "name": "Ken Mauer",
          "slug": "ken-mauer"
        }
      ]
    },
    {
      "pts": 17,
      "reb": 6,
      "ast": 1,
      "team_abbr": "MIA",
      "opp_abbr": "DET",
      "game_date": "2009-03-22",
      "game_id": "0020801041",
      "crew": [
        {
          "name": "Tony Brothers",
          "slug": "tony-brothers"
        },
        {
          "name": "Scott Foster",
          "slug": "scott-foster"
        },
        {
          "name": "Zach Zarba",
          "slug": "zach-zarba"
        }
      ]
    },
    {
      "pts": 17,
      "reb": 8,
      "ast": 1,
      "team_abbr": "TOR",
      "opp_abbr": "IND",
      "game_date": "2008-12-10",
      "game_id": "0020800314",
      "crew": [
        {
          "name": "Eli Roe",
          "slug": "eli-roe"
        },
        {
          "name": "Mark Ayotte",
          "slug": "mark-ayotte"
        },
        {
          "name": "Eddie Rush",
          "slug": "eddie-rush"
        }
      ]
    },
    {
      "pts": 16,
      "reb": 3,
      "ast": 0,
      "team_abbr": "TOR",
      "opp_abbr": "LAC",
      "game_date": "2008-02-08",
      "game_id": "0020700726",
      "crew": [
        {
          "name": "Jimmy Clark",
          "slug": "jimmy-clark"
        },
        {
          "name": "Derrick Collins",
          "slug": "derrick-collins"
        },
        {
          "name": "Jason Phillips",
          "slug": "jason-phillips"
        }
      ]
    },
    {
      "pts": 16,
      "reb": 8,
      "ast": 2,
      "team_abbr": "TOR",
      "opp_abbr": "NYK",
      "game_date": "2008-02-22",
      "game_id": "0020700806",
      "crew": [
        {
          "name": "John Goble",
          "slug": "john-goble"
        },
        {
          "name": "David Jones",
          "slug": "david-jones"
        },
        {
          "name": "Jack Nies",
          "slug": "jack-nies"
        }
      ]
    },
    {
      "pts": 16,
      "reb": 5,
      "ast": 1,
      "team_abbr": "TOR",
      "opp_abbr": "CHA",
      "game_date": "2008-04-04",
      "game_id": "0020701126",
      "crew": [
        {
          "name": "Luis Grillo",
          "slug": "luis-grillo"
        },
        {
          "name": "Joe Forte",
          "slug": "joe-forte"
        },
        {
          "name": "Sean Wright",
          "slug": "sean-wright"
        }
      ]
    },
    {
      "pts": 16,
      "reb": 5,
      "ast": 0,
      "team_abbr": "TOR",
      "opp_abbr": "LAC",
      "game_date": "2007-12-18",
      "game_id": "0020700364",
      "crew": [
        {
          "name": "James Capers",
          "slug": "james-capers"
        },
        {
          "name": "Mark Lindsay",
          "slug": "mark-lindsay"
        },
        {
          "name": "Jimmy Clark",
          "slug": "jimmy-clark"
        }
      ]
    },
    {
      "pts": 16,
      "reb": 3,
      "ast": 3,
      "team_abbr": "TOR",
      "opp_abbr": "PHX",
      "game_date": "2009-01-18",
      "game_id": "0020800599",
      "crew": [
        {
          "name": "Tony Brothers",
          "slug": "tony-brothers"
        },
        {
          "name": "Scott Wall",
          "slug": "scott-wall"
        },
        {
          "name": "Derek Richardson",
          "slug": "derek-richardson"
        }
      ]
    }
  ]
}