{
  "summary": {
    "name": "Jaren Jackson Jr.",
    "slug": "jaren-jackson-jr",
    "first_season": "2018-19",
    "last_season": "2025-26",
    "teams": [
      "MEM",
      "UTA"
    ],
    "games_total": 484,
    "eras": [
      "espn",
      "nba"
    ]
  },
  "ref_splits": [
    {
      "ref_name": "Gediminas Petraitis",
      "ref_slug": "gediminas-petraitis",
      "player_id": "1628991",
      "n_games": 27,
      "pts_with_ref": 18.96,
      "pts_baseline": 18.41,
      "pts_swing": 0.55,
      "reb_with_ref": 6.52,
      "reb_baseline": 5.72,
      "reb_swing": 0.8,
      "ast_with_ref": 1.37,
      "ast_baseline": 1.49,
      "ast_swing": -0.12,
      "seasons": [
        "2018-19",
        "2019-20",
        "2020-21",
        "2021-22",
        "2022-23",
        "2023-24",
        "2024-25",
        "2025-26"
      ]
    },
    {
      "ref_name": "Tony Brothers",
      "ref_slug": "tony-brothers",
      "player_id": "1628991",
      "n_games": 27,
      "pts_with_ref": 16.52,
      "pts_baseline": 17.49,
      "pts_swing": -0.98,
      "reb_with_ref": 5.44,
      "reb_baseline": 5.66,
      "reb_swing": -0.21,
      "ast_with_ref": 1.41,
      "ast_baseline": 1.37,
      "ast_swing": 0.04,
      "seasons": [
        "2018-19",
        "2019-20",
        "2020-21",
        "2021-22",
        "2022-23",
        "2023-24",
        "2024-25",
        "2025-26"
      ]
    },
    {
      "ref_name": "Karl Lane",
      "ref_slug": "karl-lane",
      "player_id": "1628991",
      "n_games": 26,
      "pts_with_ref": 18.65,
      "pts_baseline": 18.01,
      "pts_swing": 0.64,
      "reb_with_ref": 5.12,
      "reb_baseline": 5.57,
      "reb_swing": -0.46,
      "ast_with_ref": 1.5,
      "ast_baseline": 1.44,
      "ast_swing": 0.06,
      "seasons": [
        "2018-19",
        "2019-20",
        "2020-21",
        "2021-22",
        "2022-23",
        "2023-24",
        "2024-25",
        "2025-26"
      ]
    },
    {
      "ref_name": "Scott Twardoski",
      "ref_slug": "scott-twardoski",
      "player_id": "1628991",
      "n_games": 26,
      "pts_with_ref": 18.19,
      "pts_baseline": 18.71,
      "pts_swing": -0.52,
      "reb_with_ref": 4.58,
      "reb_baseline": 5.73,
      "reb_swing": -1.15,
      "ast_with_ref": 1.38,
      "ast_baseline": 1.54,
      "ast_swing": -0.16,
      "seasons": [
        "2018-19",
        "2019-20",
        "2021-22",
        "2022-23",
        "2023-24",
        "2024-25",
        "2025-26"
      ]
    },
    {
      "ref_name": "Brent Barnaky",
      "ref_slug": "brent-barnaky",
      "player_id": "1628991",
      "n_games": 25,
      "pts_with_ref": 18.04,
      "pts_baseline": 18.21,
      "pts_swing": -0.17,
      "reb_with_ref": 5.28,
      "reb_baseline": 5.61,
      "reb_swing": -0.33,
      "ast_with_ref": 1.44,
      "ast_baseline": 1.44,
      "ast_swing": -0.0,
      "seasons": [
        "2018-19",
        "2019-20",
        "2021-22",
        "2022-23",
        "2023-24",
        "2024-25",
        "2025-26"
      ]
    },
    {
      "ref_name": "Courtney Kirkland",
      "ref_slug": "courtney-kirkland",
      "player_id": "4277961",
      "n_games": 25,
      "pts_with_ref": 18.72,
      "pts_baseline": 19.5,
      "pts_swing": -0.78,
      "reb_with_ref": 5.56,
      "reb_baseline": 5.74,
      "reb_swing": -0.18,
      "ast_with_ref": 1.52,
      "ast_baseline": 1.7,
      "ast_swing": -0.18,
      "seasons": [
        "2018-19",
        "2019-20",
        "2021-22",
        "2022-23",
        "2023-24",
        "2024-25",
        "2025-26"
      ]
    },
    {
      "ref_name": "Marc Davis",
      "ref_slug": "marc-davis",
      "player_id": "1628991",
      "n_games": 25,
      "pts_with_ref": 17.84,
      "pts_baseline": 18.47,
      "pts_swing": -0.63,
      "reb_with_ref": 5.96,
      "reb_baseline": 5.94,
      "reb_swing": 0.02,
      "ast_with_ref": 1.16,
      "ast_baseline": 1.47,
      "ast_swing": -0.31,
      "seasons": [
        "2018-19",
        "2019-20",
        "2020-21",
        "2021-22",
        "2022-23",
        "2023-24",
        "2024-25",
        "2025-26"
      ]
    },
    {
      "ref_name": "Ben Taylor",
      "ref_slug": "ben-taylor",
      "player_id": "1628991",
      "n_games": 24,
      "pts_with_ref": 17.42,
      "pts_baseline": 17.95,
      "pts_swing": -0.54,
      "reb_with_ref": 5.25,
      "reb_baseline": 5.53,
      "reb_swing": -0.28,
      "ast_with_ref": 1.67,
      "ast_baseline": 1.39,
      "ast_swing": 0.28,
      "seasons": [
        "2018-19",
        "2019-20",
        "2021-22",
        "2022-23",
        "2023-24",
        "2024-25"
      ]
    },
    {
      "ref_name": "Curtis Blair",
      "ref_slug": "curtis-blair",
      "player_id": "1628991",
      "n_games": 24,
      "pts_with_ref": 18.42,
      "pts_baseline": 18.77,
      "pts_swing": -0.35,
      "reb_with_ref": 5.88,
      "reb_baseline": 5.41,
      "reb_swing": 0.47,
      "ast_with_ref": 1.38,
      "ast_baseline": 1.58,
      "ast_swing": -0.2,
      "seasons": [
        "2018-19",
        "2019-20",
        "2021-22",
        "2022-23",
        "2023-24",
        "2024-25"
      ]
    },
    {
      "ref_name": "Jacyn Goble",
      "ref_slug": "jacyn-goble",
      "player_id": "4277961",
      "n_games": 24,
      "pts_with_ref": 20.79,
      "pts_baseline": 19.59,
      "pts_swing": 1.2,
      "reb_with_ref": 4.96,
      "reb_baseline": 5.47,
      "reb_swing": -0.51,
      "ast_with_ref": 1.71,
      "ast_baseline": 1.75,
      "ast_swing": -0.04,
      "seasons": [
        "2018-19",
        "2019-20",
        "2021-22",
        "2022-23",
        "2023-24",
        "2024-25",
        "2025-26"
      ]
    },
    {
      "ref_name": "Mitchell Ervin",
      "ref_slug": "mitchell-ervin",
      "player_id": "1628991",
      "n_games": 24,
      "pts_with_ref": 16.83,
      "pts_baseline": 18.37,
      "pts_swing": -1.54,
      "reb_with_ref": 6.25,
      "reb_baseline": 5.68,
      "reb_swing": 0.57,
      "ast_with_ref": 1.71,
      "ast_baseline": 1.54,
      "ast_swing": 0.17,
      "seasons": [
        "2018-19",
        "2019-20",
        "2021-22",
        "2022-23",
        "2023-24",
        "2024-25",
        "2025-26"
      ]
    },
    {
      "ref_name": "Sean Wright",
      "ref_slug": "sean-wright",
      "player_id": "1628991",
      "n_games": 24,
      "pts_with_ref": 16.29,
      "pts_baseline": 18.53,
      "pts_swing": -2.24,
      "reb_with_ref": 5.92,
      "reb_baseline": 5.76,
      "reb_swing": 0.15,
      "ast_with_ref": 1.46,
      "ast_baseline": 1.54,
      "ast_swing": -0.08,
      "seasons": [
        "2018-19",
        "2019-20",
        "2020-21",
        "2021-22",
        "2022-23",
        "2023-24",
        "2024-25",
        "2025-26"
      ]
    },
    {
      "ref_name": "Bill Kennedy",
      "ref_slug": "bill-kennedy",
      "player_id": "1628991",
      "n_games": 23,
      "pts_with_ref": 20.78,
      "pts_baseline": 18.62,
      "pts_swing": 2.16,
      "reb_with_ref": 6.3,
      "reb_baseline": 5.87,
      "reb_swing": 0.44,
      "ast_with_ref": 1.39,
      "ast_baseline": 1.49,
      "ast_swing": -0.1,
      "seasons": [
        "2019-20",
        "2020-21",
        "2021-22",
        "2022-23",
        "2023-24",
        "2024-25",
        "2025-26"
      ]
    },
    {
      "ref_name": "Kevin Cutler",
      "ref_slug": "kevin-cutler",
      "player_id": "1628991",
      "n_games": 23,
      "pts_with_ref": 20.57,
      "pts_baseline": 18.98,
      "pts_swing": 1.59,
      "reb_with_ref": 6.17,
      "reb_baseline": 5.72,
      "reb_swing": 0.45,
      "ast_with_ref": 1.61,
      "ast_baseline": 1.56,
      "ast_swing": 0.04,
      "seasons": [
        "2018-19",
        "2019-20",
        "2020-21",
        "2021-22",
        "2022-23",
        "2023-24",
        "2024-25",
        "2025-26"
      ]
    },
    {
      "ref_name": "Ray Acosta",
      "ref_slug": "ray-acosta",
      "player_id": "1628991",
      "n_games": 23,
      "pts_with_ref": 15.17,
      "pts_baseline": 18.9,
      "pts_swing": -3.72,
      "reb_with_ref": 4.78,
      "reb_baseline": 5.56,
      "reb_swing": -0.78,
      "ast_with_ref": 1.26,
      "ast_baseline": 1.61,
      "ast_swing": -0.35,
      "seasons": [
        "2018-19",
        "2019-20",
        "2020-21",
        "2021-22",
        "2022-23",
        "2023-24",
        "2024-25",
        "2025-26"
      ]
    },
    {
      "ref_name": "Tyler Ford",
      "ref_slug": "tyler-ford",
      "player_id": "1628991",
      "n_games": 23,
      "pts_with_ref": 19.74,
      "pts_baseline": 17.39,
      "pts_swing": 2.35,
      "reb_with_ref": 5.65,
      "reb_baseline": 5.62,
      "reb_swing": 0.03,
      "ast_with_ref": 1.61,
      "ast_baseline": 1.36,
      "ast_swing": 0.25,
      "seasons": [
        "2018-19",
        "2020-21",
        "2021-22",
        "2022-23",
        "2023-24",
        "2024-25",
        "2025-26"
      ]
    },
    {
      "ref_name": "Brian Forte",
      "ref_slug": "brian-forte",
      "player_id": "1628991",
      "n_games": 22,
      "pts_with_ref": 21.45,
      "pts_baseline": 18.74,
      "pts_swing": 2.72,
      "reb_with_ref": 4.86,
      "reb_baseline": 5.78,
      "reb_swing": -0.91,
      "ast_with_ref": 1.77,
      "ast_baseline": 1.52,
      "ast_swing": 0.26,
      "seasons": [
        "2018-19",
        "2019-20",
        "2020-21",
        "2021-22",
        "2022-23",
        "2023-24",
        "2024-25",
        "2025-26"
      ]
    },
    {
      "ref_name": "John Goble",
      "ref_slug": "john-goble",
      "player_id": "1628991",
      "n_games": 22,
      "pts_with_ref": 17.0,
      "pts_baseline": 18.33,
      "pts_swing": -1.33,
      "reb_with_ref": 5.64,
      "reb_baseline": 5.88,
      "reb_swing": -0.24,
      "ast_with_ref": 1.23,
      "ast_baseline": 1.42,
      "ast_swing": -0.19,
      "seasons": [
        "2019-20",
        "2020-21",
        "2021-22",
        "2022-23",
        "2023-24",
        "2024-25",
        "2025-26"
      ]
    },
    {
      "ref_name": "Josh Tiven",
      "ref_slug": "josh-tiven",
      "player_id": "1628991",
      "n_games": 22,
      "pts_with_ref": 18.5,
      "pts_baseline": 17.79,
      "pts_swing": 0.71,
      "reb_with_ref": 5.64,
      "reb_baseline": 5.85,
      "reb_swing": -0.21,
      "ast_with_ref": 1.18,
      "ast_baseline": 1.33,
      "ast_swing": -0.15,
      "seasons": [
        "2018-19",
        "2019-20",
        "2020-21",
        "2021-22",
        "2022-23",
        "2024-25"
      ]
    },
    {
      "ref_name": "Justin Van Duyne",
      "ref_slug": "justin-van-duyne",
      "player_id": "1628991",
      "n_games": 22,
      "pts_with_ref": 19.36,
      "pts_baseline": 18.43,
      "pts_swing": 0.93,
      "reb_with_ref": 6.05,
      "reb_baseline": 5.43,
      "reb_swing": 0.62,
      "ast_with_ref": 1.55,
      "ast_baseline": 1.5,
      "ast_swing": 0.04,
      "seasons": [
        "2018-19",
        "2019-20",
        "2021-22",
        "2022-23",
        "2023-24",
        "2024-25",
        "2025-26"
      ]
    },
    {
      "ref_name": "Michael Smith",
      "ref_slug": "michael-smith",
      "player_id": "1628991",
      "n_games": 22,
      "pts_with_ref": 19.23,
      "pts_baseline": 18.18,
      "pts_swing": 1.05,
      "reb_with_ref": 6.64,
      "reb_baseline": 5.88,
      "reb_swing": 0.76,
      "ast_with_ref": 1.68,
      "ast_baseline": 1.4,
      "ast_swing": 0.28,
      "seasons": [
        "2018-19",
        "2019-20",
        "2020-21",
        "2021-22",
        "2022-23",
        "2023-24",
        "2024-25"
      ]
    },
    {
      "ref_name": "Natalie Sago",
      "ref_slug": "natalie-sago",
      "player_id": "1628991",
      "n_games": 22,
      "pts_with_ref": 14.82,
      "pts_baseline": 17.98,
      "pts_swing": -3.16,
      "reb_with_ref": 5.05,
      "reb_baseline": 5.45,
      "reb_swing": -0.41,
      "ast_with_ref": 1.27,
      "ast_baseline": 1.52,
      "ast_swing": -0.25,
      "seasons": [
        "2018-19",
        "2019-20",
        "2021-22",
        "2022-23",
        "2023-24",
        "2024-25",
        "2025-26"
      ]
    },
    {
      "ref_name": "Nick Buchert",
      "ref_slug": "nick-buchert",
      "player_id": "1628991",
      "n_games": 22,
      "pts_with_ref": 17.14,
      "pts_baseline": 18.05,
      "pts_swing": -0.91,
      "reb_with_ref": 5.32,
      "reb_baseline": 5.55,
      "reb_swing": -0.23,
      "ast_with_ref": 1.77,
      "ast_baseline": 1.4,
      "ast_swing": 0.38,
      "seasons": [
        "2018-19",
        "2019-20",
        "2021-22",
        "2022-23",
        "2024-25",
        "2025-26"
      ]
    },
    {
      "ref_name": "Ed Malloy",
      "ref_slug": "ed-malloy",
      "player_id": "4277961",
      "n_games": 21,
      "pts_with_ref": 19.81,
      "pts_baseline": 19.02,
      "pts_swing": 0.79,
      "reb_with_ref": 5.71,
      "reb_baseline": 5.64,
      "reb_swing": 0.07,
      "ast_with_ref": 1.24,
      "ast_baseline": 1.68,
      "ast_swing": -0.44,
      "seasons": [
        "2018-19",
        "2019-20",
        "2020-21",
        "2021-22",
        "2022-23",
        "2023-24",
        "2024-25",
        "2025-26"
      ]
    },
    {
      "ref_name": "Aaron Smith",
      "ref_slug": "aaron-smith",
      "player_id": "1628991",
      "n_games": 20,
      "pts_with_ref": 15.65,
      "pts_baseline": 18.38,
      "pts_swing": -2.73,
      "reb_with_ref": 5.1,
      "reb_baseline": 5.4,
      "reb_swing": -0.3,
      "ast_with_ref": 1.1,
      "ast_baseline": 1.57,
      "ast_swing": -0.47,
      "seasons": [
        "2018-19",
        "2019-20",
        "2020-21",
        "2021-22",
        "2022-23",
        "2023-24",
        "2024-25",
        "2025-26"
      ]
    },
    {
      "ref_name": "Eric Lewis",
      "ref_slug": "eric-lewis",
      "player_id": "1628991",
      "n_games": 20,
      "pts_with_ref": 15.0,
      "pts_baseline": 16.83,
      "pts_swing": -1.83,
      "reb_with_ref": 6.1,
      "reb_baseline": 5.77,
      "reb_swing": 0.33,
      "ast_with_ref": 1.6,
      "ast_baseline": 1.13,
      "ast_swing": 0.47,
      "seasons": [
        "2018-19",
        "2019-20",
        "2020-21",
        "2021-22",
        "2022-23"
      ]
    },
    {
      "ref_name": "James Capers",
      "ref_slug": "james-capers",
      "player_id": "1628991",
      "n_games": 20,
      "pts_with_ref": 17.05,
      "pts_baseline": 17.48,
      "pts_swing": -0.43,
      "reb_with_ref": 5.6,
      "reb_baseline": 5.36,
      "reb_swing": 0.24,
      "ast_with_ref": 1.4,
      "ast_baseline": 1.45,
      "ast_swing": -0.05,
      "seasons": [
        "2018-19",
        "2019-20",
        "2020-21",
        "2021-22",
        "2022-23",
        "2023-24",
        "2024-25",
        "2025-26"
      ]
    },
    {
      "ref_name": "Jonathan Sterling",
      "ref_slug": "jonathan-sterling",
      "player_id": "1628991",
      "n_games": 20,
      "pts_with_ref": 18.8,
      "pts_baseline": 19.23,
      "pts_swing": -0.43,
      "reb_with_ref": 5.85,
      "reb_baseline": 5.85,
      "reb_swing": 0.0,
      "ast_with_ref": 1.35,
      "ast_baseline": 1.51,
      "ast_swing": -0.16,
      "seasons": [
        "2019-20",
        "2021-22",
        "2022-23",
        "2023-24",
        "2024-25",
        "2025-26"
      ]
    },
    {
      "ref_name": "Mark Lindsay",
      "ref_slug": "mark-lindsay",
      "player_id": "1628991",
      "n_games": 20,
      "pts_with_ref": 18.5,
      "pts_baseline": 18.49,
      "pts_swing": 0.01,
      "reb_with_ref": 6.0,
      "reb_baseline": 5.52,
      "reb_swing": 0.48,
      "ast_with_ref": 2.1,
      "ast_baseline": 1.54,
      "ast_swing": 0.56,
      "seasons": [
        "2018-19",
        "2019-20",
        "2021-22",
        "2022-23",
        "2023-24",
        "2024-25",
        "2025-26"
      ]
    },
    {
      "ref_name": "James Williams",
      "ref_slug": "james-williams",
      "player_id": "1628991",
      "n_games": 19,
      "pts_with_ref": 19.89,
      "pts_baseline": 17.89,
      "pts_swing": 2.01,
      "reb_with_ref": 6.05,
      "reb_baseline": 5.73,
      "reb_swing": 0.33,
      "ast_with_ref": 1.32,
      "ast_baseline": 1.37,
      "ast_swing": -0.06,
      "seasons": [
        "2018-19",
        "2019-20",
        "2020-21",
        "2021-22",
        "2022-23",
        "2023-24",
        "2024-25"
      ]
    },
    {
      "ref_name": "JB DeRosa",
      "ref_slug": "jb-derosa",
      "player_id": "1628991",
      "n_games": 19,
      "pts_with_ref": 19.21,
      "pts_baseline": 18.46,
      "pts_swing": 0.75,
      "reb_with_ref": 6.79,
      "reb_baseline": 5.57,
      "reb_swing": 1.22,
      "ast_with_ref": 1.53,
      "ast_baseline": 1.52,
      "ast_swing": 0.0,
      "seasons": [
        "2018-19",
        "2019-20",
        "2021-22",
        "2022-23",
        "2023-24",
        "2024-25"
      ]
    },
    {
      "ref_name": "Kevin Scott",
      "ref_slug": "kevin-scott",
      "player_id": "1628991",
      "n_games": 19,
      "pts_with_ref": 18.26,
      "pts_baseline": 18.35,
      "pts_swing": -0.09,
      "reb_with_ref": 5.11,
      "reb_baseline": 5.63,
      "reb_swing": -0.53,
      "ast_with_ref": 1.53,
      "ast_baseline": 1.47,
      "ast_swing": 0.06,
      "seasons": [
        "2019-20",
        "2020-21",
        "2021-22",
        "2022-23",
        "2023-24",
        "2024-25",
        "2025-26"
      ]
    },
    {
      "ref_name": "Phenizee Ransom",
      "ref_slug": "phenizee-ransom",
      "player_id": "1628991",
      "n_games": 19,
      "pts_with_ref": 17.63,
      "pts_baseline": 19.06,
      "pts_swing": -1.43,
      "reb_with_ref": 5.95,
      "reb_baseline": 5.6,
      "reb_swing": 0.34,
      "ast_with_ref": 2.11,
      "ast_baseline": 1.59,
      "ast_swing": 0.52,
      "seasons": [
        "2018-19",
        "2019-20",
        "2021-22",
        "2022-23",
        "2023-24",
        "2024-25",
        "2025-26"
      ]
    },
    {
      "ref_name": "Zach Zarba",
      "ref_slug": "zach-zarba",
      "player_id": "1628991",
      "n_games": 19,
      "pts_with_ref": 20.37,
      "pts_baseline": 18.12,
      "pts_swing": 2.25,
      "reb_with_ref": 6.42,
      "reb_baseline": 5.8,
      "reb_swing": 0.62,
      "ast_with_ref": 1.89,
      "ast_baseline": 1.48,
      "ast_swing": 0.41,
      "seasons": [
        "2018-19",
        "2021-22",
        "2022-23",
        "2023-24",
        "2024-25",
        "2025-26"
      ]
    },
    {
      "ref_name": "Marat Kogut",
      "ref_slug": "marat-kogut",
      "player_id": "4277961",
      "n_games": 18,
      "pts_with_ref": 21.17,
      "pts_baseline": 18.48,
      "pts_swing": 2.69,
      "reb_with_ref": 4.0,
      "reb_baseline": 5.39,
      "reb_swing": -1.39,
      "ast_with_ref": 1.33,
      "ast_baseline": 1.61,
      "ast_swing": -0.28,
      "seasons": [
        "2018-19",
        "2019-20",
        "2021-22",
        "2022-23",
        "2024-25",
        "2025-26"
      ]
    },
    {
      "ref_name": "Scott Foster",
      "ref_slug": "scott-foster",
      "player_id": "1628991",
      "n_games": 18,
      "pts_with_ref": 17.61,
      "pts_baseline": 18.38,
      "pts_swing": -0.77,
      "reb_with_ref": 6.72,
      "reb_baseline": 5.85,
      "reb_swing": 0.87,
      "ast_with_ref": 1.72,
      "ast_baseline": 1.49,
      "ast_swing": 0.23,
      "seasons": [
        "2018-19",
        "2019-20",
        "2021-22",
        "2022-23",
        "2023-24",
        "2024-25",
        "2025-26"
      ]
    },
    {
      "ref_name": "Tom Washington",
      "ref_slug": "tom-washington",
      "player_id": "1628991",
      "n_games": 18,
      "pts_with_ref": 18.89,
      "pts_baseline": 17.48,
      "pts_swing": 1.41,
      "reb_with_ref": 5.39,
      "reb_baseline": 5.39,
      "reb_swing": -0.0,
      "ast_with_ref": 1.83,
      "ast_baseline": 1.44,
      "ast_swing": 0.39,
      "seasons": [
        "2018-19",
        "2019-20",
        "2020-21",
        "2021-22",
        "2023-24",
        "2024-25"
      ]
    },
    {
      "ref_name": "David Guthrie",
      "ref_slug": "david-guthrie",
      "player_id": "1628991",
      "n_games": 17,
      "pts_with_ref": 17.47,
      "pts_baseline": 18.75,
      "pts_swing": -1.28,
      "reb_with_ref": 5.18,
      "reb_baseline": 5.84,
      "reb_swing": -0.66,
      "ast_with_ref": 1.35,
      "ast_baseline": 1.52,
      "ast_swing": -0.17,
      "seasons": [
        "2019-20",
        "2020-21",
        "2021-22",
        "2022-23",
        "2023-24",
        "2024-25"
      ]
    },
    {
      "ref_name": "Eric Dalen",
      "ref_slug": "eric-dalen",
      "player_id": "1628991",
      "n_games": 17,
      "pts_with_ref": 20.12,
      "pts_baseline": 18.7,
      "pts_swing": 1.42,
      "reb_with_ref": 5.29,
      "reb_baseline": 5.43,
      "reb_swing": -0.14,
      "ast_with_ref": 1.59,
      "ast_baseline": 1.64,
      "ast_swing": -0.05,
      "seasons": [
        "2018-19",
        "2019-20",
        "2021-22",
        "2023-24",
        "2024-25",
        "2025-26"
      ]
    },
    {
      "ref_name": "Evan Scott",
      "ref_slug": "evan-scott",
      "player_id": "1628991",
      "n_games": 17,
      "pts_with_ref": 17.35,
      "pts_baseline": 18.82,
      "pts_swing": -1.47,
      "reb_with_ref": 5.35,
      "reb_baseline": 5.74,
      "reb_swing": -0.39,
      "ast_with_ref": 1.65,
      "ast_baseline": 1.55,
      "ast_swing": 0.1,
      "seasons": [
        "2018-19",
        "2019-20",
        "2020-21",
        "2021-22",
        "2022-23",
        "2023-24",
        "2024-25",
        "2025-26"
      ]
    },
    {
      "ref_name": "J.T. Orr",
      "ref_slug": "j-t-orr",
      "player_id": "1628991",
      "n_games": 17,
      "pts_with_ref": 18.59,
      "pts_baseline": 18.3,
      "pts_swing": 0.28,
      "reb_with_ref": 6.41,
      "reb_baseline": 5.31,
      "reb_swing": 1.1,
      "ast_with_ref": 2.24,
      "ast_baseline": 1.53,
      "ast_swing": 0.71,
      "seasons": [
        "2018-19",
        "2019-20",
        "2021-22",
        "2022-23",
        "2023-24",
        "2024-25",
        "2025-26"
      ]
    },
    {
      "ref_name": "Pat Fraher",
      "ref_slug": "pat-fraher",
      "player_id": "1628991",
      "n_games": 17,
      "pts_with_ref": 19.12,
      "pts_baseline": 18.73,
      "pts_swing": 0.39,
      "reb_with_ref": 5.06,
      "reb_baseline": 5.57,
      "reb_swing": -0.51,
      "ast_with_ref": 1.76,
      "ast_baseline": 1.49,
      "ast_swing": 0.28,
      "seasons": [
        "2018-19",
        "2019-20",
        "2021-22",
        "2022-23",
        "2023-24",
        "2024-25"
      ]
    },
    {
      "ref_name": "Rodney Mott",
      "ref_slug": "rodney-mott",
      "player_id": "1628991",
      "n_games": 17,
      "pts_with_ref": 17.24,
      "pts_baseline": 18.39,
      "pts_swing": -1.15,
      "reb_with_ref": 5.06,
      "reb_baseline": 5.56,
      "reb_swing": -0.5,
      "ast_with_ref": 1.53,
      "ast_baseline": 1.47,
      "ast_swing": 0.06,
      "seasons": [
        "2018-19",
        "2019-20",
        "2021-22",
        "2022-23",
        "2023-24",
        "2024-25",
        "2025-26"
      ]
    },
    {
      "ref_name": "Brandon Adair",
      "ref_slug": "brandon-adair",
      "player_id": "1628991",
      "n_games": 16,
      "pts_with_ref": 16.38,
      "pts_baseline": 18.38,
      "pts_swing": -2.0,
      "reb_with_ref": 5.56,
      "reb_baseline": 5.54,
      "reb_swing": 0.02,
      "ast_with_ref": 1.44,
      "ast_baseline": 1.45,
      "ast_swing": -0.01,
      "seasons": [
        "2018-19",
        "2019-20",
        "2020-21",
        "2021-22",
        "2022-23",
        "2023-24",
        "2024-25"
      ]
    },
    {
      "ref_name": "Derrick Collins",
      "ref_slug": "derrick-collins",
      "player_id": "1628991",
      "n_games": 16,
      "pts_with_ref": 17.0,
      "pts_baseline": 18.41,
      "pts_swing": -1.41,
      "reb_with_ref": 5.5,
      "reb_baseline": 5.68,
      "reb_swing": -0.18,
      "ast_with_ref": 1.81,
      "ast_baseline": 1.48,
      "ast_swing": 0.33,
      "seasons": [
        "2018-19",
        "2019-20",
        "2020-21",
        "2021-22",
        "2022-23",
        "2023-24",
        "2024-25",
        "2025-26"
      ]
    },
    {
      "ref_name": "Jason Goldenberg",
      "ref_slug": "jason-goldenberg",
      "player_id": "1628991",
      "n_games": 16,
      "pts_with_ref": 19.5,
      "pts_baseline": 19.07,
      "pts_swing": 0.43,
      "reb_with_ref": 5.25,
      "reb_baseline": 5.6,
      "reb_swing": -0.35,
      "ast_with_ref": 1.38,
      "ast_baseline": 1.64,
      "ast_swing": -0.27,
      "seasons": [
        "2018-19",
        "2019-20",
        "2021-22",
        "2022-23",
        "2023-24",
        "2024-25",
        "2025-26"
      ]
    },
    {
      "ref_name": "Scott Wall",
      "ref_slug": "scott-wall",
      "player_id": "1628991",
      "n_games": 16,
      "pts_with_ref": 15.81,
      "pts_baseline": 17.66,
      "pts_swing": -1.85,
      "reb_with_ref": 4.81,
      "reb_baseline": 5.56,
      "reb_swing": -0.75,
      "ast_with_ref": 1.5,
      "ast_baseline": 1.35,
      "ast_swing": 0.15,
      "seasons": [
        "2018-19",
        "2019-20",
        "2020-21",
        "2021-22",
        "2022-23",
        "2023-24"
      ]
    },
    {
      "ref_name": "Sean Corbin",
      "ref_slug": "sean-corbin",
      "player_id": "4277961",
      "n_games": 16,
      "pts_with_ref": 19.44,
      "pts_baseline": 19.88,
      "pts_swing": -0.44,
      "reb_with_ref": 6.56,
      "reb_baseline": 5.73,
      "reb_swing": 0.83,
      "ast_with_ref": 2.25,
      "ast_baseline": 1.75,
      "ast_swing": 0.5,
      "seasons": [
        "2019-20",
        "2021-22",
        "2022-23",
        "2023-24",
        "2024-25",
        "2025-26"
      ]
    },
    {
      "ref_name": "Andy Nagy",
      "ref_slug": "andy-nagy",
      "player_id": "4277961",
      "n_games": 15,
      "pts_with_ref": 18.27,
      "pts_baseline": 20.24,
      "pts_swing": -1.97,
      "reb_with_ref": 6.47,
      "reb_baseline": 5.85,
      "reb_swing": 0.61,
      "ast_with_ref": 1.8,
      "ast_baseline": 1.7,
      "ast_swing": 0.1,
      "seasons": [
        "2019-20",
        "2021-22",
        "2022-23",
        "2023-24",
        "2024-25",
        "2025-26"
      ]
    },
    {
      "ref_name": "Brett Nansel",
      "ref_slug": "brett-nansel",
      "player_id": "4277961",
      "n_games": 15,
      "pts_with_ref": 24.93,
      "pts_baseline": 19.55,
      "pts_swing": 5.38,
      "reb_with_ref": 5.93,
      "reb_baseline": 5.66,
      "reb_swing": 0.27,
      "ast_with_ref": 1.6,
      "ast_baseline": 1.67,
      "ast_swing": -0.07,
      "seasons": [
        "2018-19",
        "2019-20",
        "2021-22",
        "2022-23",
        "2023-24",
        "2024-25",
        "2025-26"
      ]
    },
    {
      "ref_name": "Jenna Schroeder",
      "ref_slug": "jenna-schroeder",
      "player_id": "4277961",
      "n_games": 15,
      "pts_with_ref": 18.47,
      "pts_baseline": 20.1,
      "pts_swing": -1.64,
      "reb_with_ref": 4.8,
      "reb_baseline": 5.5,
      "reb_swing": -0.7,
      "ast_with_ref": 1.8,
      "ast_baseline": 1.84,
      "ast_swing": -0.04,
      "seasons": [
        "2019-20",
        "2021-22",
        "2023-24",
        "2024-25",
        "2025-26"
      ]
    },
    {
      "ref_name": "Leon Wood",
      "ref_slug": "leon-wood",
      "player_id": "1628991",
      "n_games": 15,
      "pts_with_ref": 21.6,
      "pts_baseline": 17.98,
      "pts_swing": 3.62,
      "reb_with_ref": 5.8,
      "reb_baseline": 5.6,
      "reb_swing": 0.2,
      "ast_with_ref": 1.87,
      "ast_baseline": 1.48,
      "ast_swing": 0.39,
      "seasons": [
        "2018-19",
        "2019-20",
        "2020-21",
        "2021-22",
        "2022-23",
        "2023-24",
        "2025-26"
      ]
    },
    {
      "ref_name": "Tre Maddox",
      "ref_slug": "tre-maddox",
      "player_id": "1628991",
      "n_games": 15,
      "pts_with_ref": 17.07,
      "pts_baseline": 16.85,
      "pts_swing": 0.22,
      "reb_with_ref": 5.6,
      "reb_baseline": 5.49,
      "reb_swing": 0.11,
      "ast_with_ref": 1.47,
      "ast_baseline": 1.3,
      "ast_swing": 0.17,
      "seasons": [
        "2018-19",
        "2019-20",
        "2020-21",
        "2021-22",
        "2022-23",
        "2023-24",
        "2024-25",
        "2025-26"
      ]
    }
  ],
  "top_games": [
    {
      "pts": 44,
      "reb": 7,
      "ast": 2,
      "team_abbr": "MEM",
      "opp_abbr": "HOU",
      "game_date": "2023-12-14",
      "game_id": "401584942",
      "crew": [
        {
          "name": "Jason Goldenberg",
          "slug": "jason-goldenberg"
        },
        {
          "name": "David Guthrie",
          "slug": "david-guthrie"
        },
        {
          "name": "Ashley Moyer-Gleich",
          "slug": "ashley-moyer-gleich"
        }
      ]
    },
    {
      "pts": 43,
      "reb": 5,
      "ast": 1,
      "team_abbr": "MEM",
      "opp_abbr": "MIL",
      "game_date": "2019-12-13",
      "game_id": "0021900376",
      "crew": [
        {
          "name": "Ben Taylor",
          "slug": "ben-taylor"
        },
        {
          "name": "Rodney Mott",
          "slug": "rodney-mott"
        },
        {
          "name": "Leon Wood",
          "slug": "leon-wood"
        }
      ]
    },
    {
      "pts": 42,
      "reb": 4,
      "ast": 2,
      "team_abbr": "MEM",
      "opp_abbr": "SAS",
      "game_date": "2025-03-02",
      "game_id": "401705429",
      "crew": [
        {
          "name": "Marat Kogut",
          "slug": "marat-kogut"
        },
        {
          "name": "Tyler Ford",
          "slug": "tyler-ford"
        },
        {
          "name": "Suyash Mehta",
          "slug": "suyash-mehta"
        }
      ]
    },
    {
      "pts": 41,
      "reb": 4,
      "ast": 2,
      "team_abbr": "MEM",
      "opp_abbr": "DAL",
      "game_date": "2023-12-12",
      "game_id": "401584927",
      "crew": [
        {
          "name": "James Williams",
          "slug": "james-williams"
        },
        {
          "name": "Eric Dalen",
          "slug": "eric-dalen"
        },
        {
          "name": "Lauren Holtkamp",
          "slug": "lauren-holtkamp"
        }
      ]
    },
    {
      "pts": 40,
      "reb": 9,
      "ast": 3,
      "team_abbr": "MEM",
      "opp_abbr": "NOP",
      "game_date": "2023-04-05",
      "game_id": "0022201194",
      "crew": [
        {
          "name": "Scott Foster",
          "slug": "scott-foster"
        },
        {
          "name": "Dedric Taylor",
          "slug": "dedric-taylor"
        },
        {
          "name": "Brandon Schwab",
          "slug": "brandon-schwab"
        }
      ]
    },
    {
      "pts": 40,
      "reb": 7,
      "ast": 3,
      "team_abbr": "MEM",
      "opp_abbr": "DET",
      "game_date": "2024-04-01",
      "game_id": "401585716",
      "crew": [
        {
          "name": "Brent Barnaky",
          "slug": "brent-barnaky"
        },
        {
          "name": "Kevin Cutler",
          "slug": "kevin-cutler"
        },
        {
          "name": "Dannica Baroody",
          "slug": "dannica-baroody"
        }
      ]
    },
    {
      "pts": 39,
      "reb": 6,
      "ast": 1,
      "team_abbr": "MEM",
      "opp_abbr": "WAS",
      "game_date": "2024-11-09",
      "game_id": "401704757",
      "crew": [
        {
          "name": "Bill Kennedy",
          "slug": "bill-kennedy"
        },
        {
          "name": "Dedric Taylor",
          "slug": "dedric-taylor"
        },
        {
          "name": "Michael Smith",
          "slug": "michael-smith"
        }
      ]
    },
    {
      "pts": 38,
      "reb": 12,
      "ast": 4,
      "team_abbr": "MEM",
      "opp_abbr": "PHX",
      "game_date": "2025-01-01",
      "game_id": "401705019",
      "crew": [
        {
          "name": "Marc Davis",
          "slug": "marc-davis"
        },
        {
          "name": "Phenizee Ransom",
          "slug": "phenizee-ransom"
        },
        {
          "name": "JD Ralls",
          "slug": "jd-ralls"
        }
      ]
    },
    {
      "pts": 37,
      "reb": 9,
      "ast": 2,
      "team_abbr": "MEM",
      "opp_abbr": "PHX",
      "game_date": "2023-12-03",
      "game_id": "401584916",
      "crew": [
        {
          "name": "Curtis Blair",
          "slug": "curtis-blair"
        },
        {
          "name": "Rodney Mott",
          "slug": "rodney-mott"
        },
        {
          "name": "John Butler",
          "slug": "john-butler"
        }
      ]
    },
    {
      "pts": 37,
      "reb": 10,
      "ast": 2,
      "team_abbr": "MEM",
      "opp_abbr": "HOU",
      "game_date": "2023-03-22",
      "game_id": "0022201088",
      "crew": []
    }
  ]
}