{
  "summary": {
    "name": "Trayce Jackson-Davis",
    "slug": "trayce-jackson-davis",
    "first_season": "2023-24",
    "last_season": "2025-26",
    "teams": [
      "GSW",
      "TOR"
    ],
    "games_total": 197,
    "eras": [
      "espn"
    ]
  },
  "ref_splits": [
    {
      "ref_name": "Mark Lindsay",
      "ref_slug": "mark-lindsay",
      "player_id": "4431684",
      "n_games": 15,
      "pts_with_ref": 4.73,
      "pts_baseline": 5.85,
      "pts_swing": -1.12,
      "reb_with_ref": 3.33,
      "reb_baseline": 4.24,
      "reb_swing": -0.9,
      "ast_with_ref": 1.13,
      "ast_baseline": 1.23,
      "ast_swing": -0.1,
      "seasons": [
        "2023-24",
        "2024-25",
        "2025-26"
      ]
    }
  ],
  "top_games": [
    {
      "pts": 20,
      "reb": 5,
      "ast": 4,
      "team_abbr": "GSW",
      "opp_abbr": "HOU",
      "game_date": "2024-04-05",
      "game_id": "401585741",
      "crew": [
        {
          "name": "Scott Twardoski",
          "slug": "scott-twardoski"
        },
        {
          "name": "Tyler Ford",
          "slug": "tyler-ford"
        },
        {
          "name": "Natalie Sago",
          "slug": "natalie-sago"
        }
      ]
    },
    {
      "pts": 19,
      "reb": 5,
      "ast": 1,
      "team_abbr": "GSW",
      "opp_abbr": "NOP",
      "game_date": "2024-01-11",
      "game_id": "401585153",
      "crew": [
        {
          "name": "Jacyn Goble",
          "slug": "jacyn-goble"
        },
        {
          "name": "Ben Taylor",
          "slug": "ben-taylor"
        },
        {
          "name": "Scott Twardoski",
          "slug": "scott-twardoski"
        }
      ]
    },
    {
      "pts": 19,
      "reb": 9,
      "ast": 2,
      "team_abbr": "GSW",
      "opp_abbr": "NYK",
      "game_date": "2024-03-19",
      "game_id": "401585616",
      "crew": [
        {
          "name": "Zach Zarba",
          "slug": "zach-zarba"
        },
        {
          "name": "Brett Nansel",
          "slug": "brett-nansel"
        },
        {
          "name": "Andy Nagy",
          "slug": "andy-nagy"
        }
      ]
    },
    {
      "pts": 19,
      "reb": 7,
      "ast": 0,
      "team_abbr": "GSW",
      "opp_abbr": "MIA",
      "game_date": "2025-01-08",
      "game_id": "401705074",
      "crew": [
        {
          "name": "Brian Forte",
          "slug": "brian-forte"
        },
        {
          "name": "J.T. Orr",
          "slug": "j-t-orr"
        },
        {
          "name": "Mousa Dagher",
          "slug": "mousa-dagher"
        }
      ]
    },
    {
      "pts": 18,
      "reb": 8,
      "ast": 1,
      "team_abbr": "GSW",
      "opp_abbr": "CHA",
      "game_date": "2024-03-29",
      "game_id": "401585690",
      "crew": [
        {
          "name": "Derek Richardson",
          "slug": "derek-richardson"
        },
        {
          "name": "Mark Lindsay",
          "slug": "mark-lindsay"
        },
        {
          "name": "Sean Corbin",
          "slug": "sean-corbin"
        }
      ]
    },
    {
      "pts": 17,
      "reb": 6,
      "ast": 2,
      "team_abbr": "GSW",
      "opp_abbr": "DAL",
      "game_date": "2023-12-31",
      "game_id": "401585072",
      "crew": [
        {
          "name": "Tom Washington",
          "slug": "tom-washington"
        },
        {
          "name": "Scott Wall",
          "slug": "scott-wall"
        },
        {
          "name": "Kevin Scott",
          "slug": "kevin-scott"
        }
      ]
    },
    {
      "pts": 17,
      "reb": 5,
      "ast": 1,
      "team_abbr": "GSW",
      "opp_abbr": "LAL",
      "game_date": "2024-02-23",
      "game_id": "401585430",
      "crew": [
        {
          "name": "Zach Zarba",
          "slug": "zach-zarba"
        },
        {
          "name": "Marat Kogut",
          "slug": "marat-kogut"
        },
        {
          "name": "Gediminas Petraitis",
          "slug": "gediminas-petraitis"
        }
      ]
    },
    {
      "pts": 16,
      "reb": 7,
      "ast": 0,
      "team_abbr": "GSW",
      "opp_abbr": "UTA",
      "game_date": "2024-04-08",
      "game_id": "401585770",
      "crew": [
        {
          "name": "Jacyn Goble",
          "slug": "jacyn-goble"
        },
        {
          "name": "J.T. Orr",
          "slug": "j-t-orr"
        },
        {
          "name": "Matt Kallio",
          "slug": "matt-kallio"
        }
      ]
    },
    {
      "pts": 16,
      "reb": 11,
      "ast": 2,
      "team_abbr": "GSW",
      "opp_abbr": "TOR",
      "game_date": "2024-01-08",
      "game_id": "401585132",
      "crew": [
        {
          "name": "Matt Boland",
          "slug": "matt-boland"
        },
        {
          "name": "Zach Zarba",
          "slug": "zach-zarba"
        },
        {
          "name": "Sean Corbin",
          "slug": "sean-corbin"
        }
      ]
    },
    {
      "pts": 16,
      "reb": 10,
      "ast": 2,
      "team_abbr": "GSW",
      "opp_abbr": "PHX",
      "game_date": "2024-12-29",
      "game_id": "401704997",
      "crew": [
        {
          "name": "James Williams",
          "slug": "james-williams"
        },
        {
          "name": "Brian Forte",
          "slug": "brian-forte"
        },
        {
          "name": "Brett Nansel",
          "slug": "brett-nansel"
        }
      ]
    }
  ]
}