{
  "summary": {
    "name": "Troy Hudson",
    "slug": "troy-hudson",
    "first_season": "2000-01",
    "last_season": "2007-08",
    "teams": [
      "GSW",
      "MIN",
      "ORL"
    ],
    "games_total": 436,
    "eras": [
      "espn",
      "nba"
    ]
  },
  "ref_splits": [
    {
      "ref_name": "Scott Foster",
      "ref_slug": "scott-foster",
      "player_id": "353",
      "n_games": 31,
      "pts_with_ref": 9.94,
      "pts_baseline": 9.87,
      "pts_swing": 0.07,
      "reb_with_ref": 1.58,
      "reb_baseline": 1.65,
      "reb_swing": -0.07,
      "ast_with_ref": 4.06,
      "ast_baseline": 3.48,
      "ast_swing": 0.59,
      "seasons": [
        "2000-01",
        "2001-02",
        "2002-03",
        "2003-04",
        "2004-05",
        "2005-06",
        "2006-07",
        "2007-08"
      ]
    },
    {
      "ref_name": "Michael Smith",
      "ref_slug": "michael-smith",
      "player_id": "353",
      "n_games": 29,
      "pts_with_ref": 12.0,
      "pts_baseline": 10.15,
      "pts_swing": 1.85,
      "reb_with_ref": 2.1,
      "reb_baseline": 1.68,
      "reb_swing": 0.42,
      "ast_with_ref": 3.66,
      "ast_baseline": 3.58,
      "ast_swing": 0.07,
      "seasons": [
        "2000-01",
        "2001-02",
        "2002-03",
        "2003-04",
        "2004-05",
        "2005-06",
        "2006-07",
        "2007-08"
      ]
    },
    {
      "ref_name": "Dan Crawford",
      "ref_slug": "dan-crawford",
      "player_id": "353",
      "n_games": 28,
      "pts_with_ref": 8.79,
      "pts_baseline": 9.78,
      "pts_swing": -1.0,
      "reb_with_ref": 1.36,
      "reb_baseline": 1.6,
      "reb_swing": -0.24,
      "ast_with_ref": 3.36,
      "ast_baseline": 3.38,
      "ast_swing": -0.02,
      "seasons": [
        "2000-01",
        "2001-02",
        "2002-03",
        "2003-04",
        "2004-05",
        "2005-06",
        "2006-07",
        "2007-08"
      ]
    },
    {
      "ref_name": "Marc Davis",
      "ref_slug": "marc-davis",
      "player_id": "353",
      "n_games": 28,
      "pts_with_ref": 9.86,
      "pts_baseline": 9.62,
      "pts_swing": 0.24,
      "reb_with_ref": 1.54,
      "reb_baseline": 1.62,
      "reb_swing": -0.08,
      "ast_with_ref": 3.61,
      "ast_baseline": 3.4,
      "ast_swing": 0.21,
      "seasons": [
        "2000-01",
        "2001-02",
        "2002-03",
        "2003-04",
        "2004-05",
        "2005-06",
        "2006-07",
        "2007-08"
      ]
    },
    {
      "ref_name": "Eddie Rush",
      "ref_slug": "eddie-rush",
      "player_id": "353",
      "n_games": 26,
      "pts_with_ref": 9.04,
      "pts_baseline": 9.41,
      "pts_swing": -0.37,
      "reb_with_ref": 1.38,
      "reb_baseline": 1.56,
      "reb_swing": -0.17,
      "ast_with_ref": 3.54,
      "ast_baseline": 3.3,
      "ast_swing": 0.24,
      "seasons": [
        "2000-01",
        "2001-02",
        "2002-03",
        "2003-04",
        "2004-05",
        "2005-06"
      ]
    },
    {
      "ref_name": "Jason Phillips",
      "ref_slug": "jason-phillips",
      "player_id": "353",
      "n_games": 26,
      "pts_with_ref": 8.62,
      "pts_baseline": 9.05,
      "pts_swing": -0.43,
      "reb_with_ref": 1.35,
      "reb_baseline": 1.59,
      "reb_swing": -0.24,
      "ast_with_ref": 2.92,
      "ast_baseline": 3.29,
      "ast_swing": -0.37,
      "seasons": [
        "2000-01",
        "2001-02",
        "2002-03",
        "2003-04",
        "2004-05",
        "2005-06",
        "2007-08"
      ]
    },
    {
      "ref_name": "Joe Forte",
      "ref_slug": "joe-forte",
      "player_id": "353",
      "n_games": 25,
      "pts_with_ref": 12.2,
      "pts_baseline": 10.53,
      "pts_swing": 1.67,
      "reb_with_ref": 1.88,
      "reb_baseline": 1.65,
      "reb_swing": 0.23,
      "ast_with_ref": 2.48,
      "ast_baseline": 3.56,
      "ast_swing": -1.08,
      "seasons": [
        "2000-01",
        "2001-02",
        "2002-03",
        "2003-04",
        "2004-05",
        "2005-06"
      ]
    },
    {
      "ref_name": "Kevin Fehr",
      "ref_slug": "kevin-fehr",
      "player_id": "353",
      "n_games": 25,
      "pts_with_ref": 10.44,
      "pts_baseline": 9.38,
      "pts_swing": 1.06,
      "reb_with_ref": 1.48,
      "reb_baseline": 1.63,
      "reb_swing": -0.15,
      "ast_with_ref": 3.16,
      "ast_baseline": 3.43,
      "ast_swing": -0.27,
      "seasons": [
        "2000-01",
        "2001-02",
        "2002-03",
        "2003-04",
        "2004-05",
        "2005-06",
        "2006-07"
      ]
    },
    {
      "ref_name": "Mike Callahan",
      "ref_slug": "mike-callahan",
      "player_id": "353",
      "n_games": 25,
      "pts_with_ref": 11.44,
      "pts_baseline": 9.73,
      "pts_swing": 1.71,
      "reb_with_ref": 1.4,
      "reb_baseline": 1.64,
      "reb_swing": -0.24,
      "ast_with_ref": 3.08,
      "ast_baseline": 3.43,
      "ast_swing": -0.35,
      "seasons": [
        "2000-01",
        "2001-02",
        "2002-03",
        "2003-04",
        "2004-05",
        "2005-06",
        "2006-07",
        "2007-08"
      ]
    },
    {
      "ref_name": "Bob Delaney",
      "ref_slug": "bob-delaney",
      "player_id": "353",
      "n_games": 24,
      "pts_with_ref": 9.46,
      "pts_baseline": 9.23,
      "pts_swing": 0.23,
      "reb_with_ref": 1.08,
      "reb_baseline": 1.64,
      "reb_swing": -0.56,
      "ast_with_ref": 3.0,
      "ast_baseline": 3.28,
      "ast_swing": -0.28,
      "seasons": [
        "2000-01",
        "2001-02",
        "2002-03",
        "2004-05",
        "2005-06",
        "2006-07",
        "2007-08"
      ]
    },
    {
      "ref_name": "Derrick Stafford",
      "ref_slug": "derrick-stafford",
      "player_id": "353",
      "n_games": 24,
      "pts_with_ref": 9.58,
      "pts_baseline": 9.18,
      "pts_swing": 0.4,
      "reb_with_ref": 1.92,
      "reb_baseline": 1.62,
      "reb_swing": 0.3,
      "ast_with_ref": 3.12,
      "ast_baseline": 3.25,
      "ast_swing": -0.13,
      "seasons": [
        "2000-01",
        "2001-02",
        "2002-03",
        "2003-04",
        "2004-05",
        "2005-06",
        "2006-07"
      ]
    },
    {
      "ref_name": "Leroy Richardson",
      "ref_slug": "leroy-richardson",
      "player_id": "353",
      "n_games": 24,
      "pts_with_ref": 9.5,
      "pts_baseline": 9.62,
      "pts_swing": -0.12,
      "reb_with_ref": 1.96,
      "reb_baseline": 1.56,
      "reb_swing": 0.4,
      "ast_with_ref": 3.0,
      "ast_baseline": 3.21,
      "ast_swing": -0.21,
      "seasons": [
        "2000-01",
        "2001-02",
        "2002-03",
        "2004-05",
        "2005-06",
        "2006-07"
      ]
    },
    {
      "ref_name": "Mark Wunderlich",
      "ref_slug": "mark-wunderlich",
      "player_id": "353",
      "n_games": 24,
      "pts_with_ref": 9.62,
      "pts_baseline": 9.56,
      "pts_swing": 0.07,
      "reb_with_ref": 1.79,
      "reb_baseline": 1.6,
      "reb_swing": 0.19,
      "ast_with_ref": 4.25,
      "ast_baseline": 3.3,
      "ast_swing": 0.95,
      "seasons": [
        "2000-01",
        "2001-02",
        "2002-03",
        "2003-04",
        "2004-05",
        "2005-06",
        "2006-07",
        "2007-08"
      ]
    },
    {
      "ref_name": "Monty McCutchen",
      "ref_slug": "monty-mccutchen",
      "player_id": "1607",
      "n_games": 24,
      "pts_with_ref": 8.62,
      "pts_baseline": 8.46,
      "pts_swing": 0.17,
      "reb_with_ref": 1.67,
      "reb_baseline": 1.45,
      "reb_swing": 0.21,
      "ast_with_ref": 3.92,
      "ast_baseline": 3.0,
      "ast_swing": 0.92,
      "seasons": [
        "2000-01",
        "2001-02",
        "2002-03",
        "2003-04",
        "2004-05",
        "2005-06",
        "2006-07",
        "2007-08"
      ]
    },
    {
      "ref_name": "David Jones",
      "ref_slug": "david-jones",
      "player_id": "353",
      "n_games": 23,
      "pts_with_ref": 10.09,
      "pts_baseline": 9.28,
      "pts_swing": 0.8,
      "reb_with_ref": 1.57,
      "reb_baseline": 1.62,
      "reb_swing": -0.06,
      "ast_with_ref": 3.26,
      "ast_baseline": 3.35,
      "ast_swing": -0.09,
      "seasons": [
        "2000-01",
        "2001-02",
        "2002-03",
        "2003-04",
        "2004-05",
        "2005-06",
        "2006-07"
      ]
    },
    {
      "ref_name": "Jess Kersey",
      "ref_slug": "jess-kersey",
      "player_id": "1607",
      "n_games": 23,
      "pts_with_ref": 10.52,
      "pts_baseline": 9.99,
      "pts_swing": 0.53,
      "reb_with_ref": 1.3,
      "reb_baseline": 1.58,
      "reb_swing": -0.27,
      "ast_with_ref": 3.04,
      "ast_baseline": 3.53,
      "ast_swing": -0.48,
      "seasons": [
        "2000-01",
        "2001-02",
        "2002-03",
        "2003-04",
        "2004-05",
        "2005-06",
        "2006-07"
      ]
    },
    {
      "ref_name": "Rodney Mott",
      "ref_slug": "rodney-mott",
      "player_id": "353",
      "n_games": 23,
      "pts_with_ref": 9.26,
      "pts_baseline": 8.68,
      "pts_swing": 0.58,
      "reb_with_ref": 1.22,
      "reb_baseline": 1.57,
      "reb_swing": -0.35,
      "ast_with_ref": 2.61,
      "ast_baseline": 3.3,
      "ast_swing": -0.69,
      "seasons": [
        "2000-01",
        "2001-02",
        "2002-03",
        "2003-04",
        "2004-05",
        "2005-06",
        "2006-07",
        "2007-08"
      ]
    },
    {
      "ref_name": "Bennett Salvatore",
      "ref_slug": "bennett-salvatore",
      "player_id": "353",
      "n_games": 22,
      "pts_with_ref": 10.41,
      "pts_baseline": 10.14,
      "pts_swing": 0.27,
      "reb_with_ref": 2.0,
      "reb_baseline": 1.65,
      "reb_swing": 0.35,
      "ast_with_ref": 3.77,
      "ast_baseline": 3.64,
      "ast_swing": 0.14,
      "seasons": [
        "2000-01",
        "2001-02",
        "2002-03",
        "2003-04",
        "2004-05",
        "2005-06",
        "2006-07"
      ]
    },
    {
      "ref_name": "Courtney Kirkland",
      "ref_slug": "courtney-kirkland",
      "player_id": "1607",
      "n_games": 22,
      "pts_with_ref": 9.77,
      "pts_baseline": 9.41,
      "pts_swing": 0.36,
      "reb_with_ref": 1.41,
      "reb_baseline": 1.54,
      "reb_swing": -0.13,
      "ast_with_ref": 3.86,
      "ast_baseline": 3.19,
      "ast_swing": 0.68,
      "seasons": [
        "2000-01",
        "2001-02",
        "2002-03",
        "2003-04",
        "2004-05",
        "2005-06",
        "2006-07"
      ]
    },
    {
      "ref_name": "Dick Bavetta",
      "ref_slug": "dick-bavetta",
      "player_id": "353",
      "n_games": 22,
      "pts_with_ref": 8.09,
      "pts_baseline": 9.6,
      "pts_swing": -1.5,
      "reb_with_ref": 1.82,
      "reb_baseline": 1.62,
      "reb_swing": 0.2,
      "ast_with_ref": 3.95,
      "ast_baseline": 3.4,
      "ast_swing": 0.56,
      "seasons": [
        "2000-01",
        "2001-02",
        "2002-03",
        "2004-05",
        "2005-06",
        "2006-07"
      ]
    },
    {
      "ref_name": "Joe Crawford",
      "ref_slug": "joe-crawford",
      "player_id": "1607",
      "n_games": 22,
      "pts_with_ref": 11.73,
      "pts_baseline": 10.88,
      "pts_swing": 0.85,
      "reb_with_ref": 2.23,
      "reb_baseline": 1.66,
      "reb_swing": 0.56,
      "ast_with_ref": 3.86,
      "ast_baseline": 3.75,
      "ast_swing": 0.11,
      "seasons": [
        "2001-02",
        "2002-03",
        "2003-04",
        "2004-05",
        "2005-06",
        "2006-07",
        "2007-08"
      ]
    },
    {
      "ref_name": "Ron Garretson",
      "ref_slug": "ron-garretson",
      "player_id": "353",
      "n_games": 22,
      "pts_with_ref": 8.45,
      "pts_baseline": 9.12,
      "pts_swing": -0.67,
      "reb_with_ref": 1.64,
      "reb_baseline": 1.55,
      "reb_swing": 0.09,
      "ast_with_ref": 2.82,
      "ast_baseline": 3.16,
      "ast_swing": -0.35,
      "seasons": [
        "2000-01",
        "2001-02",
        "2002-03",
        "2004-05",
        "2005-06",
        "2006-07",
        "2007-08"
      ]
    },
    {
      "ref_name": "Ron Olesiak",
      "ref_slug": "ron-olesiak",
      "player_id": "353",
      "n_games": 22,
      "pts_with_ref": 6.64,
      "pts_baseline": 9.21,
      "pts_swing": -2.57,
      "reb_with_ref": 1.45,
      "reb_baseline": 1.66,
      "reb_swing": -0.2,
      "ast_with_ref": 3.14,
      "ast_baseline": 3.28,
      "ast_swing": -0.14,
      "seasons": [
        "2000-01",
        "2001-02",
        "2002-03",
        "2003-04",
        "2004-05",
        "2006-07"
      ]
    },
    {
      "ref_name": "Scott Wall",
      "ref_slug": "scott-wall",
      "player_id": "353",
      "n_games": 22,
      "pts_with_ref": 7.45,
      "pts_baseline": 8.16,
      "pts_swing": -0.7,
      "reb_with_ref": 1.41,
      "reb_baseline": 1.46,
      "reb_swing": -0.05,
      "ast_with_ref": 3.18,
      "ast_baseline": 2.85,
      "ast_swing": 0.34,
      "seasons": [
        "2000-01",
        "2001-02",
        "2002-03",
        "2003-04",
        "2004-05",
        "2005-06",
        "2006-07",
        "2007-08"
      ]
    },
    {
      "ref_name": "Sean Corbin",
      "ref_slug": "sean-corbin",
      "player_id": "353",
      "n_games": 22,
      "pts_with_ref": 9.45,
      "pts_baseline": 10.05,
      "pts_swing": -0.6,
      "reb_with_ref": 1.59,
      "reb_baseline": 1.68,
      "reb_swing": -0.09,
      "ast_with_ref": 4.05,
      "ast_baseline": 3.54,
      "ast_swing": 0.51,
      "seasons": [
        "2000-01",
        "2001-02",
        "2002-03",
        "2004-05",
        "2005-06",
        "2006-07"
      ]
    },
    {
      "ref_name": "Steve Javie",
      "ref_slug": "steve-javie",
      "player_id": "1607",
      "n_games": 22,
      "pts_with_ref": 8.0,
      "pts_baseline": 9.44,
      "pts_swing": -1.44,
      "reb_with_ref": 1.23,
      "reb_baseline": 1.57,
      "reb_swing": -0.34,
      "ast_with_ref": 3.59,
      "ast_baseline": 3.34,
      "ast_swing": 0.25,
      "seasons": [
        "2000-01",
        "2001-02",
        "2002-03",
        "2003-04",
        "2004-05",
        "2005-06",
        "2006-07"
      ]
    },
    {
      "ref_name": "Jack Nies",
      "ref_slug": "jack-nies",
      "player_id": "353",
      "n_games": 21,
      "pts_with_ref": 8.67,
      "pts_baseline": 10.59,
      "pts_swing": -1.93,
      "reb_with_ref": 1.33,
      "reb_baseline": 1.69,
      "reb_swing": -0.35,
      "ast_with_ref": 3.67,
      "ast_baseline": 3.74,
      "ast_swing": -0.08,
      "seasons": [
        "2000-01",
        "2001-02",
        "2002-03",
        "2003-04",
        "2004-05",
        "2005-06",
        "2006-07"
      ]
    },
    {
      "ref_name": "Tim Donaghy",
      "ref_slug": "tim-donaghy",
      "player_id": "353",
      "n_games": 21,
      "pts_with_ref": 11.1,
      "pts_baseline": 9.85,
      "pts_swing": 1.24,
      "reb_with_ref": 2.33,
      "reb_baseline": 1.61,
      "reb_swing": 0.73,
      "ast_with_ref": 3.52,
      "ast_baseline": 3.34,
      "ast_swing": 0.18,
      "seasons": [
        "2000-01",
        "2001-02",
        "2002-03",
        "2003-04",
        "2004-05",
        "2005-06"
      ]
    },
    {
      "ref_name": "Blane Reichelt",
      "ref_slug": "blane-reichelt",
      "player_id": "353",
      "n_games": 19,
      "pts_with_ref": 9.79,
      "pts_baseline": 10.36,
      "pts_swing": -0.57,
      "reb_with_ref": 1.53,
      "reb_baseline": 1.67,
      "reb_swing": -0.14,
      "ast_with_ref": 3.16,
      "ast_baseline": 3.46,
      "ast_swing": -0.3,
      "seasons": [
        "2000-01",
        "2001-02",
        "2002-03",
        "2003-04",
        "2004-05"
      ]
    },
    {
      "ref_name": "Ken Mauer",
      "ref_slug": "ken-mauer",
      "player_id": "1607",
      "n_games": 19,
      "pts_with_ref": 10.11,
      "pts_baseline": 9.89,
      "pts_swing": 0.21,
      "reb_with_ref": 1.37,
      "reb_baseline": 1.57,
      "reb_swing": -0.2,
      "ast_with_ref": 3.89,
      "ast_baseline": 3.49,
      "ast_swing": 0.41,
      "seasons": [
        "2001-02",
        "2002-03",
        "2003-04",
        "2004-05",
        "2005-06",
        "2006-07"
      ]
    },
    {
      "ref_name": "Tony Brothers",
      "ref_slug": "tony-brothers",
      "player_id": "353",
      "n_games": 19,
      "pts_with_ref": 9.53,
      "pts_baseline": 10.11,
      "pts_swing": -0.59,
      "reb_with_ref": 1.79,
      "reb_baseline": 1.68,
      "reb_swing": 0.11,
      "ast_with_ref": 3.16,
      "ast_baseline": 3.64,
      "ast_swing": -0.49,
      "seasons": [
        "2000-01",
        "2001-02",
        "2002-03",
        "2003-04",
        "2004-05",
        "2006-07"
      ]
    },
    {
      "ref_name": "Derek Richardson",
      "ref_slug": "derek-richardson",
      "player_id": "353",
      "n_games": 18,
      "pts_with_ref": 10.22,
      "pts_baseline": 10.8,
      "pts_swing": -0.58,
      "reb_with_ref": 1.94,
      "reb_baseline": 1.75,
      "reb_swing": 0.19,
      "ast_with_ref": 4.5,
      "ast_baseline": 3.91,
      "ast_swing": 0.59,
      "seasons": [
        "2000-01",
        "2001-02",
        "2002-03",
        "2003-04",
        "2004-05",
        "2005-06"
      ]
    },
    {
      "ref_name": "Bennie Adams",
      "ref_slug": "bennie-adams",
      "player_id": "353",
      "n_games": 17,
      "pts_with_ref": 6.59,
      "pts_baseline": 9.51,
      "pts_swing": -2.92,
      "reb_with_ref": 1.71,
      "reb_baseline": 1.66,
      "reb_swing": 0.04,
      "ast_with_ref": 2.71,
      "ast_baseline": 3.47,
      "ast_swing": -0.77,
      "seasons": [
        "2000-01",
        "2001-02",
        "2002-03",
        "2003-04",
        "2004-05",
        "2005-06",
        "2007-08"
      ]
    },
    {
      "ref_name": "Derrick Collins",
      "ref_slug": "derrick-collins",
      "player_id": "1607",
      "n_games": 17,
      "pts_with_ref": 9.53,
      "pts_baseline": 9.95,
      "pts_swing": -0.42,
      "reb_with_ref": 1.24,
      "reb_baseline": 1.65,
      "reb_swing": -0.41,
      "ast_with_ref": 2.82,
      "ast_baseline": 3.54,
      "ast_swing": -0.72,
      "seasons": [
        "2001-02",
        "2002-03",
        "2004-05",
        "2005-06",
        "2006-07",
        "2007-08"
      ]
    },
    {
      "ref_name": "Tom Washington",
      "ref_slug": "tom-washington",
      "player_id": "1607",
      "n_games": 17,
      "pts_with_ref": 11.06,
      "pts_baseline": 9.84,
      "pts_swing": 1.21,
      "reb_with_ref": 1.35,
      "reb_baseline": 1.5,
      "reb_swing": -0.15,
      "ast_with_ref": 3.88,
      "ast_baseline": 3.35,
      "ast_swing": 0.53,
      "seasons": [
        "2000-01",
        "2001-02",
        "2002-03",
        "2003-04",
        "2004-05",
        "2005-06",
        "2006-07"
      ]
    },
    {
      "ref_name": "Bill Spooner",
      "ref_slug": "bill-spooner",
      "player_id": "353",
      "n_games": 16,
      "pts_with_ref": 13.5,
      "pts_baseline": 11.87,
      "pts_swing": 1.63,
      "reb_with_ref": 2.19,
      "reb_baseline": 1.9,
      "reb_swing": 0.28,
      "ast_with_ref": 3.44,
      "ast_baseline": 4.29,
      "ast_swing": -0.85,
      "seasons": [
        "2000-01",
        "2001-02",
        "2002-03",
        "2004-05"
      ]
    },
    {
      "ref_name": "Gary Benson",
      "ref_slug": "gary-benson",
      "player_id": "353",
      "n_games": 16,
      "pts_with_ref": 10.12,
      "pts_baseline": 9.04,
      "pts_swing": 1.09,
      "reb_with_ref": 1.31,
      "reb_baseline": 1.61,
      "reb_swing": -0.3,
      "ast_with_ref": 3.56,
      "ast_baseline": 3.2,
      "ast_swing": 0.37,
      "seasons": [
        "2000-01",
        "2001-02",
        "2002-03",
        "2003-04",
        "2004-05"
      ]
    },
    {
      "ref_name": "Greg Willard",
      "ref_slug": "greg-willard",
      "player_id": "1607",
      "n_games": 16,
      "pts_with_ref": 10.56,
      "pts_baseline": 10.47,
      "pts_swing": 0.1,
      "reb_with_ref": 1.12,
      "reb_baseline": 1.65,
      "reb_swing": -0.53,
      "ast_with_ref": 3.06,
      "ast_baseline": 3.77,
      "ast_swing": -0.71,
      "seasons": [
        "2000-01",
        "2001-02",
        "2002-03",
        "2004-05",
        "2005-06",
        "2006-07"
      ]
    },
    {
      "ref_name": "James Capers",
      "ref_slug": "james-capers",
      "player_id": "353",
      "n_games": 16,
      "pts_with_ref": 7.88,
      "pts_baseline": 9.33,
      "pts_swing": -1.45,
      "reb_with_ref": 1.19,
      "reb_baseline": 1.57,
      "reb_swing": -0.38,
      "ast_with_ref": 2.75,
      "ast_baseline": 3.39,
      "ast_swing": -0.64,
      "seasons": [
        "2000-01",
        "2001-02",
        "2002-03",
        "2004-05",
        "2005-06",
        "2007-08"
      ]
    },
    {
      "ref_name": "Luis Grillo",
      "ref_slug": "luis-grillo",
      "player_id": "353",
      "n_games": 16,
      "pts_with_ref": 10.0,
      "pts_baseline": 10.53,
      "pts_swing": -0.53,
      "reb_with_ref": 1.62,
      "reb_baseline": 1.68,
      "reb_swing": -0.05,
      "ast_with_ref": 3.75,
      "ast_baseline": 3.52,
      "ast_swing": 0.23,
      "seasons": [
        "2000-01",
        "2001-02",
        "2002-03",
        "2004-05",
        "2005-06"
      ]
    },
    {
      "ref_name": "Pat Fraher",
      "ref_slug": "pat-fraher",
      "player_id": "1607",
      "n_games": 16,
      "pts_with_ref": 11.0,
      "pts_baseline": 10.11,
      "pts_swing": 0.89,
      "reb_with_ref": 1.81,
      "reb_baseline": 1.61,
      "reb_swing": 0.2,
      "ast_with_ref": 3.06,
      "ast_baseline": 3.47,
      "ast_swing": -0.41,
      "seasons": [
        "2001-02",
        "2002-03",
        "2003-04",
        "2004-05",
        "2005-06",
        "2006-07"
      ]
    },
    {
      "ref_name": "Phil Robinson",
      "ref_slug": "phil-robinson",
      "player_id": "1607",
      "n_games": 16,
      "pts_with_ref": 10.44,
      "pts_baseline": 8.47,
      "pts_swing": 1.97,
      "reb_with_ref": 1.56,
      "reb_baseline": 1.51,
      "reb_swing": 0.05,
      "ast_with_ref": 3.12,
      "ast_baseline": 3.03,
      "ast_swing": 0.09,
      "seasons": [
        "2000-01",
        "2001-02",
        "2002-03",
        "2003-04",
        "2004-05",
        "2005-06",
        "2006-07"
      ]
    },
    {
      "ref_name": "Leon Wood",
      "ref_slug": "leon-wood",
      "player_id": "1607",
      "n_games": 15,
      "pts_with_ref": 10.27,
      "pts_baseline": 9.31,
      "pts_swing": 0.95,
      "reb_with_ref": 1.33,
      "reb_baseline": 1.54,
      "reb_swing": -0.21,
      "ast_with_ref": 2.67,
      "ast_baseline": 3.19,
      "ast_swing": -0.53,
      "seasons": [
        "2000-01",
        "2001-02",
        "2002-03",
        "2003-04",
        "2004-05",
        "2005-06",
        "2006-07"
      ]
    }
  ],
  "top_games": [
    {
      "pts": 37,
      "reb": 2,
      "ast": 10,
      "team_abbr": "MIN",
      "opp_abbr": "LAL",
      "game_date": "2003-04-23",
      "game_id": "230422016",
      "crew": [
        {
          "name": "Jack Nies",
          "slug": "jack-nies"
        },
        {
          "name": "Scott Foster",
          "slug": "scott-foster"
        },
        {
          "name": "Tom Washington",
          "slug": "tom-washington"
        }
      ]
    },
    {
      "pts": 34,
      "reb": 3,
      "ast": 1,
      "team_abbr": "ORL",
      "opp_abbr": "PHX",
      "game_date": "2002-03-14",
      "game_id": "220313019",
      "crew": [
        {
          "name": "Ted Bernhardt",
          "slug": "ted-bernhardt"
        },
        {
          "name": "Blane Reichelt",
          "slug": "blane-reichelt"
        },
        {
          "name": "Derrick Collins",
          "slug": "derrick-collins"
        }
      ]
    },
    {
      "pts": 31,
      "reb": 4,
      "ast": 5,
      "team_abbr": "MIN",
      "opp_abbr": "SEA",
      "game_date": "2003-04-03",
      "game_id": "230402016",
      "crew": [
        {
          "name": "Jess Kersey",
          "slug": "jess-kersey"
        },
        {
          "name": "Joe Forte",
          "slug": "joe-forte"
        },
        {
          "name": "Mark Wunderlich",
          "slug": "mark-wunderlich"
        }
      ]
    },
    {
      "pts": 31,
      "reb": 3,
      "ast": 6,
      "team_abbr": "MIN",
      "opp_abbr": "DAL",
      "game_date": "2003-01-30",
      "game_id": "230130006",
      "crew": [
        {
          "name": "Don Vaden",
          "slug": "don-vaden"
        },
        {
          "name": "Ronnie Nunn",
          "slug": "ronnie-nunn"
        },
        {
          "name": "Tony Brothers",
          "slug": "tony-brothers"
        }
      ]
    },
    {
      "pts": 30,
      "reb": 4,
      "ast": 2,
      "team_abbr": "ORL",
      "opp_abbr": "NJN",
      "game_date": "2001-01-03",
      "game_id": "210102019",
      "crew": [
        {
          "name": "Tommy Nunez Jr.",
          "slug": "tommy-nunez"
        },
        {
          "name": "Leroy Richardson",
          "slug": "leroy-richardson"
        },
        {
          "name": "Scott Foster",
          "slug": "scott-foster"
        }
      ]
    },
    {
      "pts": 30,
      "reb": 3,
      "ast": 3,
      "team_abbr": "MIN",
      "opp_abbr": "SAS",
      "game_date": "2003-03-13",
      "game_id": "230312016",
      "crew": [
        {
          "name": "Ron Garretson",
          "slug": "ron-garretson"
        },
        {
          "name": "David Jones",
          "slug": "david-jones"
        },
        {
          "name": "Kevin Fehr",
          "slug": "kevin-fehr"
        }
      ]
    },
    {
      "pts": 29,
      "reb": 4,
      "ast": 3,
      "team_abbr": "MIN",
      "opp_abbr": "NJN",
      "game_date": "2004-02-25",
      "game_id": "0020300827",
      "crew": [
        {
          "name": "Ed Malloy",
          "slug": "ed-malloy"
        },
        {
          "name": "Ken Mauer",
          "slug": "ken-mauer"
        },
        {
          "name": "Dan Crawford",
          "slug": "dan-crawford"
        }
      ]
    },
    {
      "pts": 29,
      "reb": 3,
      "ast": 6,
      "team_abbr": "ORL",
      "opp_abbr": "NYK",
      "game_date": "2002-04-09",
      "game_id": "220409018",
      "crew": [
        {
          "name": "Joe Crawford",
          "slug": "joe-crawford"
        },
        {
          "name": "Monty McCutchen",
          "slug": "monty-mccutchen"
        },
        {
          "name": "Courtney Kirkland",
          "slug": "courtney-kirkland"
        }
      ]
    },
    {
      "pts": 28,
      "reb": 4,
      "ast": 4,
      "team_abbr": "MIN",
      "opp_abbr": "LAL",
      "game_date": "2003-04-27",
      "game_id": "230427013",
      "crew": [
        {
          "name": "Joe Crawford",
          "slug": "joe-crawford"
        },
        {
          "name": "Joe Forte",
          "slug": "joe-forte"
        },
        {
          "name": "Greg Willard",
          "slug": "greg-willard"
        }
      ]
    },
    {
      "pts": 27,
      "reb": 2,
      "ast": 4,
      "team_abbr": "MIN",
      "opp_abbr": "LAL",
      "game_date": "2003-04-25",
      "game_id": "230424013",
      "crew": [
        {
          "name": "Ronnie Nunn",
          "slug": "ronnie-nunn"
        },
        {
          "name": "Leroy Richardson",
          "slug": "leroy-richardson"
        },
        {
          "name": "Bill Spooner",
          "slug": "bill-spooner"
        }
      ]
    }
  ]
}